[
  {
    "name": "Ліжко 140",
    "desc": "",
    "images": [
      "/static/img/catalogue/b171.jpg",
      "/static/img/catalogue/bg5430.jpg",
      "/static/img/catalogue/bg2197.jpg",
      "/static/img/catalogue/bg5087.jpg",
      "/static/img/catalogue/bg1075.jpg",
      "/static/img/catalogue/bg1076.jpg",
      "/static/img/catalogue/bg1077.jpg",
      "/static/img/catalogue/bg1078.jpg",
      "/static/img/catalogue/bg1079.jpg",
      "/static/img/catalogue/bg1080.jpg",
      "/static/img/catalogue/bg1081.jpg"
    ],
    "price": "4758 грн",
    "specs": [
      "висота, мм: 750",
      "ширина, мм: 1444",
      "глибина, мм: 2042",
      "вага, кг: 67,45",
      "розмір упаковки, мм: 2010х110х750",
      "колір ДСП: Бук, Венге, Вільха, Горіх, Яблуня, Дуб сонома",
      "матеріал: ламіноване ДСП"
    ]
  },
  {
    "name": "Ліжко 90",
    "desc": "",
    "images": [
      "/static/img/catalogue/b172.jpg",
      "/static/img/catalogue/bg5434.jpg",
      "/static/img/catalogue/bg2198.jpg",
      "/static/img/catalogue/bg5084.jpg",
      "/static/img/catalogue/bg1082.jpg",
      "/static/img/catalogue/bg1083.jpg",
      "/static/img/catalogue/bg1084.jpg",
      "/static/img/catalogue/bg1085.jpg",
      "/static/img/catalogue/bg1086.jpg",
      "/static/img/catalogue/bg1087.jpg",
      "/static/img/catalogue/bg1088.jpg"
    ],
    "price": "3411 грн",
    "specs": [
      "висота, мм: 700",
      "ширина, мм: 944",
      "глибина, мм: 2042",
      "вага, кг: 51,4",
      "розмір упаковки, мм: 2010х60х920",
      "колір ДСП: Бук, Венге, Вільха, Горіх, Яблуня, Дуб сонома",
      "матеріал: ламіноване ДСП"
    ]
  },
  {
    "name": "Ліжко 90+2",
    "desc": "",
    "images": [
      "/static/img/catalogue/b173.jpg",
      "/static/img/catalogue/bg5438.jpg",
      "/static/img/catalogue/bg2199.jpg",
      "/static/img/catalogue/bg5082.jpg",
      "/static/img/catalogue/bg1089.jpg",
      "/static/img/catalogue/bg1090.jpg",
      "/static/img/catalogue/bg1091.jpg",
      "/static/img/catalogue/bg1092.jpg",
      "/static/img/catalogue/bg1093.jpg",
      "/static/img/catalogue/bg1094.jpg",
      "/static/img/catalogue/bg1095.jpg"
    ],
    "price": "4667 грн",
    "specs": [
      "висота, мм: 650",
      "ширина, мм: 944",
      "глибина, мм: 2042",
      "вага, кг: 71",
      "розмір упаковки, мм: 2015х915х65",
      "колір ДСП: Бук, Вільха, Горіх, Яблуня, Дуб сонома, Венге темний",
      "матеріал: ламіноване ДСП"
    ]
  },
  {
    "name": "Ліжко Твікс-2",
    "desc": "",
    "images": [
      "/static/img/catalogue/b174.jpg",
      "/static/img/catalogue/bg5447.jpg",
      "/static/img/catalogue/bg5071.jpg",
      "/static/img/catalogue/bg2200.jpg",
      "/static/img/catalogue/bg1096.jpg",
      "/static/img/catalogue/bg1097.jpg",
      "/static/img/catalogue/bg1098.jpg",
      "/static/img/catalogue/bg1099.jpg",
      "/static/img/catalogue/bg1100.jpg",
      "/static/img/catalogue/bg1101.jpg",
      "/static/img/catalogue/bg1102.jpg"
    ],
    "price": "7829 грн",
    "specs": [
      "висота, мм: 1522",
      "ширина, мм: 908",
      "глибина, мм: 1974",
      "колір ДСП: Бук, Венге, Вільха, Горіх, Яблуня, Дуб сонома",
      "матеріал: ламіноване ДСП",
      "розмір упаковки ч.1, мм: 1910х708х64",
      "вага, кг: 47,8",
      "розмір упаковки ч.2, мм: 1910х742х64",
      "вага, кг: 48,4",
      "рекомендований розмір матраца, мм: 1900х700"
    ]
  },
  {
    "name": "Ліжко Твікс",
    "desc": "",
    "images": [
      "/static/img/catalogue/b175.jpg",
      "/static/img/catalogue/bg5446.jpg",
      "/static/img/catalogue/bg5070.jpg",
      "/static/img/catalogue/bg2201.jpg",
      "/static/img/catalogue/bg1103.jpg",
      "/static/img/catalogue/bg1104.jpg",
      "/static/img/catalogue/bg1105.jpg",
      "/static/img/catalogue/bg1106.jpg",
      "/static/img/catalogue/bg1107.jpg",
      "/static/img/catalogue/bg1108.jpg"
    ],
    "price": "7172 грн",
    "specs": [
      "висота, мм: 1522",
      "ширина, мм: 776",
      "глибина, мм: 2108",
      "колір ДСП: Бук, Венге, Вільха, Горіх, Яблуня, Дуб сонома",
      "матеріал: ламіноване ДСП",
      "розмір упаковки ч.1, мм: 1930х742х80",
      "вага, кг: 59,6",
      "розмір упаковки ч.2, мм: 1920х742х48",
      "вага, кг: 36,6",
      "рекомендований розмір матраца, мм: 1900х700"
    ]
  },
  {
    "name": "Ліжко Універсал",
    "desc": "",
    "images": [
      "/static/img/catalogue/b176.jpg",
      "/static/img/catalogue/bg5448.jpg",
      "/static/img/catalogue/bg5073.jpg",
      "/static/img/catalogue/bg2202.jpg",
      "/static/img/catalogue/bg1109.jpg",
      "/static/img/catalogue/bg1110.jpg",
      "/static/img/catalogue/bg1111.jpg",
      "/static/img/catalogue/bg1112.jpg",
      "/static/img/catalogue/bg1113.jpg",
      "/static/img/catalogue/bg1114.jpg",
      "/static/img/catalogue/bg1115.jpg"
    ],
    "price": "8831 грн",
    "specs": [
      "висота, мм: 1060",
      "ширина, мм: 892",
      "глибина, мм: 1942",
      "колір ДСП: Бук, Венге, Вільха, Горіх, Яблуня, Дуб сонома",
      "матеріал: ламіноване ДСП",
      "розмір упаковки ч.1, мм: 1915х1057х64",
      "вага, кг: 74,4",
      "розмір упаковки ч.2, мм: 1095х745х80",
      "вага, кг: 38,8",
      "рекомендований розмір матраца, мм: 1900х700"
    ]
  },
  {
    "name": "Стіл-ліжко 90",
    "desc": "",
    "images": [
      "/static/img/catalogue/b427.jpg",
      "/static/img/catalogue/bg2115.jpg",
      "/static/img/catalogue/bg2116.jpg",
      "/static/img/catalogue/bg2119.jpg",
      "/static/img/catalogue/bg2117.jpg",
      "/static/img/catalogue/bg2118.jpg",
      "/static/img/catalogue/bg2120.jpg",
      "/static/img/catalogue/bg2121.jpg",
      "/static/img/catalogue/bg5453.jpg",
      "/static/img/catalogue/bg5086.jpg"
    ],
    "price": "3587 грн",
    "specs": [
      "висота, мм: 766",
      "ширина, мм: 944",
      "глибина, мм: 2133",
      "колір ДСП: Бук, Венге, Вільха, Горіх, Яблуня, Дуб сонома, Німфея Альба",
      "матеріал: ламіноване ДСП"
    ]
  },
  {
    "name": "Стіл-ліжко 140",
    "desc": "",
    "images": [
      "/static/img/catalogue/b428.jpg",
      "/static/img/catalogue/bg5451.jpg",
      "/static/img/catalogue/bg2122.jpg",
      "/static/img/catalogue/bg2126.jpg",
      "/static/img/catalogue/bg2124.jpg",
      "/static/img/catalogue/bg2123.jpg",
      "/static/img/catalogue/bg2125.jpg",
      "/static/img/catalogue/bg2128.jpg",
      "/static/img/catalogue/bg2127.jpg"
    ],
    "price": "4740 грн",
    "specs": [
      "висота, мм: 766",
      "ширина, мм: 1444",
      "глибина, мм: 2133",
      "колір ДСП: Бук, Венге, Вільха, Горіх, Яблуня, Дуб сонома, Німфея Альба",
      "матеріал: ламіноване ДСП"
    ]
  },
  {
    "name": "Стіл-ліжко 160",
    "desc": "",
    "images": [
      "/static/img/catalogue/b429.jpg",
      "/static/img/catalogue/bg5452.jpg",
      "/static/img/catalogue/bg2129.jpg",
      "/static/img/catalogue/bg2131.jpg",
      "/static/img/catalogue/bg2130.jpg",
      "/static/img/catalogue/bg2132.jpg",
      "/static/img/catalogue/bg2134.jpg",
      "/static/img/catalogue/bg2133.jpg",
      "/static/img/catalogue/bg5085.jpg",
      "/static/img/catalogue/bg2135.jpg"
    ],
    "price": "5210 грн",
    "specs": [
      "висота, мм: 766",
      "ширина, мм: 1644",
      "глибина, мм: 2133",
      "колір ДСП: Бук, Венге, Вільха, Горіх, Яблуня, Дуб сонома, Німфея Альба",
      "матеріал: ламіноване ДСП"
    ]
  },
  {
    "name": "Ліжко 80",
    "desc": "",
    "images": [
      "/static/img/catalogue/b458.jpg",
      "/static/img/catalogue/bg5432.jpg",
      "/static/img/catalogue/bg2449.jpg",
      "/static/img/catalogue/bg2451.jpg",
      "/static/img/catalogue/bg2453.jpg",
      "/static/img/catalogue/bg2455.jpg",
      "/static/img/catalogue/bg2454.jpg",
      "/static/img/catalogue/bg2452.jpg",
      "/static/img/catalogue/bg2450.jpg",
      "/static/img/catalogue/bg5080.jpg"
    ],
    "price": "3530 грн",
    "specs": [
      "висота, мм: 800(500)",
      "ширина, мм: 845",
      "глибина, мм: 2042",
      "колір ДСП: Бук, Вільха, Горіх, Яблуня, Дуб сонома, Венге темний",
      "матеріал: ламіноване ДСП"
    ]
  },
  {
    "name": "Ліжко 90+2С",
    "desc": "",
    "images": [
      "/static/img/catalogue/b460.jpg",
      "/static/img/catalogue/bg5081.jpg",
      "/static/img/catalogue/bg2466.jpg",
      "/static/img/catalogue/bg2467.jpg",
      "/static/img/catalogue/bg2463.jpg",
      "/static/img/catalogue/bg2469.jpg",
      "/static/img/catalogue/bg2464.jpg",
      "/static/img/catalogue/bg2465.jpg",
      "/static/img/catalogue/bg2468.jpg",
      "/static/img/catalogue/bg5437.jpg"
    ],
    "price": "6147 грн",
    "specs": [
      "висота, мм: 700(400)",
      "ширина, мм: 944",
      "глибина, мм: 2042",
      "колір ДСП: Бук, Вільха, Горіх, Яблуня, Дуб сонома, Венге темний",
      "матеріал: ламіноване ДСП"
    ]
  },
  {
    "name": "Ліжко Класіка - 80",
    "desc": "",
    "images": [
      "/static/img/catalogue/b482.jpg",
      "/static/img/catalogue/bg5440.jpg",
      "/static/img/catalogue/bg2779.jpg",
      "/static/img/catalogue/bg2772.jpg",
      "/static/img/catalogue/bg2774.jpg",
      "/static/img/catalogue/bg2773.jpg",
      "/static/img/catalogue/bg2776.jpg",
      "/static/img/catalogue/bg2777.jpg",
      "/static/img/catalogue/bg2775.jpg",
      "/static/img/catalogue/bg2778.jpg",
      "/static/img/catalogue/bg5078.jpg"
    ],
    "price": "3681 грн",
    "specs": [
      "висота, мм: 860",
      "ширина, мм: 852",
      "глибина, мм: 2042",
      "колір ДСП: Бук, Вільха, Горіх, Яблуня, Дуб сонома, Венге комбі, Дуб сонома/Німфея Альба, Німфея Альба",
      "матеріал: ламіноване ДСП"
    ]
  },
  {
    "name": "Ліжко Модерн - 80",
    "desc": "",
    "images": [
      "/static/img/catalogue/b483.jpg",
      "/static/img/catalogue/bg5443.jpg",
      "/static/img/catalogue/bg5076.jpg",
      "/static/img/catalogue/bg2783.jpg",
      "/static/img/catalogue/bg2786.jpg",
      "/static/img/catalogue/bg2780.jpg",
      "/static/img/catalogue/bg2787.jpg",
      "/static/img/catalogue/bg2781.jpg",
      "/static/img/catalogue/bg2782.jpg",
      "/static/img/catalogue/bg2784.jpg",
      "/static/img/catalogue/bg2785.jpg"
    ],
    "price": "3762 грн",
    "specs": [
      "висота, мм: 800",
      "ширина, мм: 852",
      "глибина, мм: 2132",
      "колір ДСП: Бук, Вільха, Горіх, Яблуня, Дуб сонома, Німфея Альба, Венге комбі, Дуб сонома/Німфея Альба",
      "матеріал: ламіноване ДСП"
    ]
  },
  {
    "name": "Ліжко Класика 140",
    "desc": "",
    "images": [
      "/static/img/catalogue/b484.jpg",
      "/static/img/catalogue/bg5441.jpg",
      "/static/img/catalogue/bg2795.jpg",
      "/static/img/catalogue/bg2788.jpg",
      "/static/img/catalogue/bg2789.jpg",
      "/static/img/catalogue/bg2790.jpg",
      "/static/img/catalogue/bg2791.jpg",
      "/static/img/catalogue/bg2792.jpg",
      "/static/img/catalogue/bg2793.jpg",
      "/static/img/catalogue/bg2794.jpg",
      "/static/img/catalogue/bg5079.jpg"
    ],
    "price": "5287 грн",
    "specs": [
      "висота, мм: 860",
      "ширина, мм: 1452",
      "глибина, мм: 2042",
      "колір ДСП: Бук, Вільха, Горіх, Яблуня, Дуб сонома, Венге комбі, Дуб сонома/Німфея Альба",
      "матеріал: ламіноване ДСП"
    ]
  },
  {
    "name": "Ліжко Модерн 140",
    "desc": "",
    "images": [
      "/static/img/catalogue/b485.jpg",
      "/static/img/catalogue/bg5444.jpg",
      "/static/img/catalogue/bg5077.jpg",
      "/static/img/catalogue/bg2796.jpg"
    ],
    "price": "5144 грн",
    "specs": [
      "висота, мм: 800",
      "ширина, мм: 1452",
      "глибина, мм: 2132",
      "колір ДСП: Бук, Вільха, Горіх, Яблуня, Дуб сонома, Венге комбі, Дуб сонома/Німфея Альба",
      "матеріал: ламіноване ДСП"
    ]
  },
  {
    "name": "Ліжко Класика 160",
    "desc": "",
    "images": [
      "/static/img/catalogue/b486.jpg",
      "/static/img/catalogue/bg5442.jpg",
      "/static/img/catalogue/bg2806.jpg",
      "/static/img/catalogue/bg2802.jpg",
      "/static/img/catalogue/bg2799.jpg",
      "/static/img/catalogue/bg2803.jpg",
      "/static/img/catalogue/bg2800.jpg",
      "/static/img/catalogue/bg2798.jpg",
      "/static/img/catalogue/bg2797.jpg",
      "/static/img/catalogue/bg2801.jpg",
      "/static/img/catalogue/bg2804.jpg",
      "/static/img/catalogue/bg2805.jpg",
      "/static/img/catalogue/bg2807.jpg"
    ],
    "price": "5730 грн",
    "specs": [
      "висота, мм: 860",
      "ширина, мм: 1652",
      "глибина, мм: 2042",
      "колір ДСП: Бук, Вільха, Горіх, Яблуня, Дуб сонома, Венге комбі, Дуб сонома/Німфея Альба",
      "матеріал: ламіноване ДСП"
    ]
  },
  {
    "name": "Ліжко Модерн 160",
    "desc": "",
    "images": [
      "/static/img/catalogue/b487.jpg",
      "/static/img/catalogue/bg5445.jpg",
      "/static/img/catalogue/bg2808.jpg"
    ],
    "price": "5654 грн",
    "specs": [
      "висота, мм: 800",
      "ширина, мм: 1652",
      "глибина, мм: 2132",
      "колір ДСП: Бук, Вільха, Горіх, Яблуня, Дуб сонома, Венге комбі, Дуб сонома/Німфея Альба",
      "матеріал: ламіноване ДСП"
    ]
  },
  {
    "name": "Ліжко 80+70",
    "desc": "",
    "images": [
      "/static/img/catalogue/b488.jpg",
      "/static/img/catalogue/bg5433.jpg",
      "/static/img/catalogue/bg5075.jpg",
      "/static/img/catalogue/bg2809.jpg",
      "/static/img/catalogue/bg2810.jpg",
      "/static/img/catalogue/bg2811.jpg",
      "/static/img/catalogue/bg2813.jpg",
      "/static/img/catalogue/bg2817.jpg",
      "/static/img/catalogue/bg2820.jpg",
      "/static/img/catalogue/bg2812.jpg",
      "/static/img/catalogue/bg2814.jpg",
      "/static/img/catalogue/bg2816.jpg",
      "/static/img/catalogue/bg2815.jpg",
      "/static/img/catalogue/bg2818.jpg",
      "/static/img/catalogue/bg2819.jpg"
    ],
    "price": "6346 грн",
    "specs": [
      "висота, мм: 750(330)",
      "ширина, мм: 846(758)",
      "глибина, мм: 2042(2000)",
      "колір ДСП: Бук, Вільха, Горіх, Яблуня, Дуб сонома, Венге темний, Німфея Альба",
      "матеріал: ламіноване ДСП"
    ]
  },
  {
    "name": "Ліжко Універсал-2",
    "desc": "",
    "images": [
      "/static/img/catalogue/b576.jpg",
      "/static/img/catalogue/bg5449.jpg",
      "/static/img/catalogue/bg4233.jpg",
      "/static/img/catalogue/bg5072.jpg",
      "/static/img/catalogue/bg4237.jpg",
      "/static/img/catalogue/bg4232.jpg",
      "/static/img/catalogue/bg4231.jpg",
      "/static/img/catalogue/bg4235.jpg",
      "/static/img/catalogue/bg4234.jpg",
      "/static/img/catalogue/bg4236.jpg"
    ],
    "price": "11991 грн",
    "specs": [
      "висота, мм: 1408",
      "ширина, мм: 744",
      "глибина, мм: 2076",
      "колір ДСП: Бук, Вільха, Горіх, Яблуня, Дуб сонома, Венге темний, Німфея Альба",
      "матеріал: ламіноване ДСП",
      "розмір упаковки ч.2, мм: 1000х402х132",
      "рекомендований розмір матраца, мм: 1900х700"
    ]
  },
  {
    "name": "Ліжко Сицилія 140 + вклад",
    "desc": "",
    "images": [
      "/static/img/catalogue/b611.jpg",
      "/static/img/catalogue/bg4471.jpg"
    ],
    "price": "11396 грн",
    "specs": [
      "висота, мм: 1060",
      "ширина, мм: 1510",
      "глибина, мм: 2350",
      "матеріал: дерев'яний масив",
      "вид деревини: сосна",
      "основа під матрас: гнуті ортопедичні ламелі",
      "матеріал покриття: фарба, лак"
    ]
  },
  {
    "name": "Ліжко Сицилія 160 + вклад",
    "desc": "",
    "images": [
      "/static/img/catalogue/b612.jpg",
      "/static/img/catalogue/bg4470.jpg"
    ],
    "price": "11748 грн",
    "specs": [
      "висота, мм: 1060",
      "ширина, мм: 1710",
      "глибина, мм: 2350",
      "матеріал: дерев'яний масив",
      "вид деревини: сосна",
      "основа під матрас: гнуті ортопедичні ламелі",
      "матеріал покриття: фарба, лак"
    ]
  },
  {
    "name": "Ліжко Сицилія 180 + вклад",
    "desc": "",
    "images": [
      "/static/img/catalogue/b613.jpg",
      "/static/img/catalogue/bg4469.jpg"
    ],
    "price": "12100 грн",
    "specs": [
      "висота, мм: 1060",
      "ширина, мм: 1910",
      "глибина, мм: 2350",
      "матеріал: дерев'яний масив",
      "вид деревини: сосна",
      "основа під матрас: гнуті ортопедичні ламелі",
      "матеріал покриття: фарба, лак"
    ]
  },
  {
    "name": "Ліжко Сицилія міні 90 + вклад",
    "desc": "",
    "images": [
      "/static/img/catalogue/b614.jpg",
      "/static/img/catalogue/bg4466.jpg",
      "/static/img/catalogue/bg4467.jpg"
    ],
    "price": "7762 грн",
    "specs": [
      "висота, мм: 1060",
      "ширина, мм: 1010",
      "глибина, мм: 2350",
      "матеріал: дерев'яний масив",
      "вид деревини: сосна",
      "основа під матрас: гнуті ортопедичні ламелі",
      "матеріал покриття: фарба, лак"
    ]
  },
  {
    "name": "Ліжко Верджинія 140 + вклад",
    "desc": "",
    "images": [
      "/static/img/catalogue/b615.jpg",
      "/static/img/catalogue/bg4473.jpg",
      "/static/img/catalogue/bg4474.jpg",
      "/static/img/catalogue/bg4472.jpg"
    ],
    "price": "11146 грн",
    "specs": [
      "висота, мм: 1100",
      "ширина, мм: 1590",
      "глибина, мм: 2140",
      "матеріал: дерев'яний масив",
      "вид деревини: сосна",
      "основа під матрас: гнуті ортопедичні ламелі",
      "матеріал покриття: фарба, лак"
    ]
  },
  {
    "name": "Ліжко Верджинія 160 + вклад",
    "desc": "",
    "images": [
      "/static/img/catalogue/b616.jpg",
      "/static/img/catalogue/bg4476.jpg",
      "/static/img/catalogue/bg4477.jpg",
      "/static/img/catalogue/bg4475.jpg"
    ],
    "price": "11492 грн",
    "specs": [
      "висота, мм: 1100",
      "ширина, мм: 1790",
      "глибина, мм: 2140",
      "матеріал: дерев'яний масив",
      "вид деревини: сосна",
      "основа під матрас: гнуті ортопедичні ламелі",
      "матеріал покриття: фарба, лак"
    ]
  },
  {
    "name": "Ліжко Верджинія 180 + вклад",
    "desc": "",
    "images": [
      "/static/img/catalogue/b617.jpg",
      "/static/img/catalogue/bg4479.jpg",
      "/static/img/catalogue/bg4480.jpg",
      "/static/img/catalogue/bg4478.jpg"
    ],
    "price": "11836 грн",
    "specs": [
      "висота, мм: 1100",
      "ширина, мм: 1990",
      "глибина, мм: 2140",
      "матеріал: дерев'яний масив",
      "вид деревини: сосна",
      "основа під матрас: гнуті ортопедичні ламелі",
      "матеріал покриття: фарба, лак"
    ]
  },
  {
    "name": "Ліжко Прованс 140 + вклад",
    "desc": "",
    "images": [
      "/static/img/catalogue/b618.jpg",
      "/static/img/catalogue/bg4482.jpg",
      "/static/img/catalogue/bg4481.jpg"
    ],
    "price": "12247 грн",
    "specs": [
      "висота, мм: 920",
      "ширина, мм: 1590",
      "глибина, мм: 2140",
      "матеріал: дерев'яний масив",
      "вид деревини: сосна",
      "основа під матрац: гнуті ортопедичні ламелі",
      "матеріал покриття: фарба, лак"
    ]
  },
  {
    "name": "Ліжко Прованс 160 + вклад",
    "desc": "",
    "images": [
      "/static/img/catalogue/b619.jpg",
      "/static/img/catalogue/bg4484.jpg",
      "/static/img/catalogue/bg4483.jpg"
    ],
    "price": "12626 грн",
    "specs": [
      "висота, мм: 920",
      "ширина, мм: 1790",
      "глибина, мм: 2140",
      "матеріал: дерев'яний масив",
      "вид деревини: сосна",
      "основа під матрац: гнуті ортопедичні ламелі",
      "матеріал покриття: фарба, лак"
    ]
  },
  {
    "name": "Ліжко Прованс 180 + вклад",
    "desc": "",
    "images": [
      "/static/img/catalogue/b620.jpg",
      "/static/img/catalogue/bg4486.jpg",
      "/static/img/catalogue/bg4485.jpg"
    ],
    "price": "13004 грн",
    "specs": [
      "висота, мм: 920",
      "ширина, мм: 1990",
      "глибина, мм: 2140",
      "матеріал: дерев'яний масив",
      "вид деревини: сосна",
      "основа під матрац: гнуті ортопедичні ламелі",
      "матеріал покриття: фарба, лак"
    ]
  },
  {
    "name": "Ліжко Манхеттен 140 + вклад",
    "desc": "",
    "images": [
      "/static/img/catalogue/b621.jpg",
      "/static/img/catalogue/bg4488.jpg",
      "/static/img/catalogue/bg4487.jpg"
    ],
    "price": "10812 грн",
    "specs": [
      "висота, мм: 840",
      "ширина, мм: 1590",
      "глибина, мм: 2180",
      "матеріал: дерев'яний масив",
      "вид деревини: сосна",
      "основа під матрац: гнуті ортопедичні ламелі",
      "матеріал покриття: фарба, лак"
    ]
  },
  {
    "name": "Ліжко Манхеттен 160 + вклад",
    "desc": "",
    "images": [
      "/static/img/catalogue/b622.jpg",
      "/static/img/catalogue/bg4490.jpg",
      "/static/img/catalogue/bg4489.jpg"
    ],
    "price": "11147 грн",
    "specs": [
      "висота, мм: 840",
      "ширина, мм: 1790",
      "глибина, мм: 2180",
      "матеріал: дерев'яний масив",
      "вид деревини: сосна",
      "основа під матрац: гнуті ортопедичні ламелі",
      "матеріал покриття: фарба, лак"
    ]
  },
  {
    "name": "Ліжко Манхеттен 180 + вклад",
    "desc": "",
    "images": [
      "/static/img/catalogue/b623.jpg",
      "/static/img/catalogue/bg4492.jpg",
      "/static/img/catalogue/bg4491.jpg"
    ],
    "price": "11482 грн",
    "specs": [
      "висота, мм: 840",
      "ширина, мм: 1990",
      "глибина, мм: 2180",
      "матеріал: дерев'яний масив",
      "вид деревини: сосна",
      "основа під матрац: гнуті ортопедичні ламелі",
      "матеріал покриття: фарба, лак"
    ]
  },
  {
    "name": "Ліжко Манхеттен 90 + вклад",
    "desc": "",
    "images": [
      "/static/img/catalogue/b624.jpg",
      "/static/img/catalogue/bg4494.jpg",
      "/static/img/catalogue/bg4493.jpg"
    ],
    "price": "9759 грн",
    "specs": [
      "висота, мм: 840",
      "ширина, мм: 1090",
      "глибина, мм: 2180",
      "матеріал: дерев'яний масив",
      "вид деревини: сосна",
      "основа під матрац: гнуті ортопедичні ламелі",
      "матеріал покриття: фарба, лак"
    ]
  },
  {
    "name": "Ліжко Тоскана 140 + вклад",
    "desc": "",
    "images": [
      "/static/img/catalogue/b625.jpg",
      "/static/img/catalogue/bg4496.jpg",
      "/static/img/catalogue/bg4495.jpg"
    ],
    "price": "10769 грн",
    "specs": [
      "висота, мм: 840",
      "ширина, мм: 1500",
      "глибина, мм: 2090",
      "матеріал: дерев'яний масив",
      "вид деревини: сосна",
      "основа під матрац: гнуті ортопедичні ламелі",
      "матеріал покриття: фарба, лак"
    ]
  },
  {
    "name": "Ліжко Тоскана 160 + вклад",
    "desc": "",
    "images": [
      "/static/img/catalogue/b626.jpg",
      "/static/img/catalogue/bg4498.jpg",
      "/static/img/catalogue/bg4497.jpg"
    ],
    "price": "11101 грн",
    "specs": [
      "висота, мм: 840",
      "ширина, мм: 1700",
      "глибина, мм: 2090",
      "матеріал: дерев'яний масив",
      "вид деревини: сосна",
      "основа під матрац: гнуті ортопедичні ламелі",
      "матеріал покриття: фарба, лак"
    ]
  },
  {
    "name": "Ліжко Тоскана 180 + вклад",
    "desc": "",
    "images": [
      "/static/img/catalogue/b627.jpg",
      "/static/img/catalogue/bg4500.jpg",
      "/static/img/catalogue/bg4499.jpg"
    ],
    "price": "11433 грн",
    "specs": [
      "висота, мм: 840",
      "ширина, мм: 1900",
      "глибина, мм: 2090",
      "матеріал: дерев'яний масив",
      "вид деревини: сосна",
      "основа під матрац: гнуті ортопедичні ламелі",
      "матеріал покриття: фарба, лак"
    ]
  },
  {
    "name": "Ліжко Тоскана 90 + вклад",
    "desc": "",
    "images": [
      "/static/img/catalogue/b628.jpg",
      "/static/img/catalogue/bg4502.jpg"
    ],
    "price": "9717 грн",
    "specs": [
      "висота, мм: 840",
      "ширина, мм: 1000",
      "глибина, мм: 2090",
      "матеріал: дерев'яний масив",
      "вид деревини: сосна",
      "основа під матрац: гнуті ортопедичні ламелі",
      "матеріал покриття: фарба, лак"
    ]
  },
  {
    "name": "Ліжко Палермо 140 + вклад",
    "desc": "",
    "images": [
      "/static/img/catalogue/b629.jpg",
      "/static/img/catalogue/bg4503.jpg",
      "/static/img/catalogue/bg4504.jpg"
    ],
    "price": "9918 грн",
    "specs": [
      "висота, мм: 840",
      "ширина, мм: 1550",
      "глибина, мм: 2240",
      "матеріал: дерев'яний масив",
      "вид деревини: сосна",
      "основа під матрац: гнуті ортопедичні ламелі",
      "матеріал покриття: фарба, лак"
    ]
  },
  {
    "name": "Ліжко Палермо 160 + вклад",
    "desc": "",
    "images": [
      "/static/img/catalogue/b630.jpg",
      "/static/img/catalogue/bg4505.jpg",
      "/static/img/catalogue/bg4506.jpg"
    ],
    "price": "10223 грн",
    "specs": [
      "висота, мм: 840",
      "ширина, мм: 1750",
      "глибина, мм: 2240",
      "матеріал: дерев'яний масив",
      "вид деревини: сосна",
      "основа під матрац: гнуті ортопедичні ламелі",
      "матеріал покриття: фарба, лак"
    ]
  },
  {
    "name": "Ліжко Палермо 180 + вклад",
    "desc": "",
    "images": [
      "/static/img/catalogue/b631.jpg",
      "/static/img/catalogue/bg4507.jpg",
      "/static/img/catalogue/bg4508.jpg"
    ],
    "price": "10529 грн",
    "specs": [
      "висота, мм: 840",
      "ширина, мм: 1950",
      "глибина, мм: 2240",
      "матеріал: дерев'яний масив",
      "вид деревини: сосна",
      "основа під матрац: гнуті ортопедичні ламелі",
      "матеріал покриття: фарба, лак"
    ]
  },
  {
    "name": "Ліжко Палермо 90 + вклад",
    "desc": "",
    "images": [
      "/static/img/catalogue/b632.jpg",
      "/static/img/catalogue/bg4509.jpg",
      "/static/img/catalogue/bg4510.jpg"
    ],
    "price": "8950 грн",
    "specs": [
      "висота, мм: 840",
      "ширина, мм: 1050",
      "глибина, мм: 2240",
      "матеріал: дерев'яний масив",
      "вид деревини: сосна",
      "основа під матрац: гнуті ортопедичні ламелі",
      "матеріал покриття: фарба, лак"
    ]
  },
  {
    "name": "Ліжко Марсель 140 + вклад",
    "desc": "",
    "images": [
      "/static/img/catalogue/b633.jpg",
      "/static/img/catalogue/bg4511.jpg"
    ],
    "price": "6467 грн",
    "specs": [
      "висота, мм: 900",
      "ширина, мм: 1500",
      "глибина, мм: 2130",
      "матеріал: дерев'яний масив",
      "вид деревини: сосна",
      "основа під матрац: гнуті ортопедичні ламелі",
      "матеріал покриття: фарба, лак"
    ]
  },
  {
    "name": "Ліжко Марсель 160 + вклад",
    "desc": "",
    "images": [
      "/static/img/catalogue/b634.jpg",
      "/static/img/catalogue/bg4512.jpg"
    ],
    "price": "6607 грн",
    "specs": [
      "висота, мм: 900",
      "ширина, мм: 1700",
      "глибина, мм: 2130",
      "матеріал: дерев'яний масив",
      "вид деревини: сосна",
      "основа під матрац: гнуті ортопедичні ламелі",
      "матеріал покриття: фарба, лак"
    ]
  },
  {
    "name": "Ліжко Марсель 180 + вклад",
    "desc": "",
    "images": [
      "/static/img/catalogue/b635.jpg",
      "/static/img/catalogue/bg4513.jpg"
    ],
    "price": "6895 грн",
    "specs": [
      "висота, мм: 900",
      "ширина, мм: 1900",
      "глибина, мм: 2130",
      "матеріал: дерев'яний масив",
      "вид деревини: сосна",
      "основа під матрац: гнуті ортопедичні ламелі",
      "матеріал покриття: фарба, лак"
    ]
  },
  {
    "name": "Ліжко Марсель 90 + вклад",
    "desc": "",
    "images": [
      "/static/img/catalogue/b636.jpg",
      "/static/img/catalogue/bg4514.jpg"
    ],
    "price": "6180 грн",
    "specs": [
      "висота, мм: 900",
      "ширина, мм: 1000",
      "глибина, мм: 2130",
      "матеріал: дерев'яний масив",
      "вид деревини: сосна",
      "основа під матрац: гнуті ортопедичні ламелі",
      "матеріал покриття: фарба, лак"
    ]
  },
  {
    "name": "Ліжко Далас 140 + вклад",
    "desc": "",
    "images": [
      "/static/img/catalogue/b637.jpg",
      "/static/img/catalogue/bg4515.jpg",
      "/static/img/catalogue/bg4517.jpg",
      "/static/img/catalogue/bg4516.jpg"
    ],
    "price": "8275 грн",
    "specs": [
      "висота, мм: 920",
      "ширина, мм: 1550",
      "глибина, мм: 2130",
      "матеріал: дерев'яний масив",
      "вид деревини: сосна",
      "основа під матрац: гнуті ортопедичні ламелі",
      "матеріал покриття: фарба, лак"
    ]
  },
  {
    "name": "Ліжко Далас 160 + вклад",
    "desc": "",
    "images": [
      "/static/img/catalogue/b638.jpg",
      "/static/img/catalogue/bg4518.jpg",
      "/static/img/catalogue/bg4520.jpg",
      "/static/img/catalogue/bg4519.jpg"
    ],
    "price": "8532 грн",
    "specs": [
      "висота, мм: 920",
      "ширина, мм: 1750",
      "глибина, мм: 2130",
      "матеріал: дерев'яний масив",
      "вид деревини: сосна",
      "основа під матрац: гнуті ортопедичні ламелі",
      "матеріал покриття: фарба, лак"
    ]
  },
  {
    "name": "Ліжко Далас 180 + вклад",
    "desc": "",
    "images": [
      "/static/img/catalogue/b639.jpg",
      "/static/img/catalogue/bg4521.jpg",
      "/static/img/catalogue/bg4523.jpg",
      "/static/img/catalogue/bg4522.jpg"
    ],
    "price": "8786 грн",
    "specs": [
      "висота, мм: 920",
      "ширина, мм: 1950",
      "глибина, мм: 2130",
      "матеріал: дерев'яний масив",
      "вид деревини: сосна",
      "основа під матрац: гнуті ортопедичні ламелі",
      "матеріал покриття: фарба, лак"
    ]
  },
  {
    "name": "Ліжко Далас 90 + вклад",
    "desc": "",
    "images": [
      "/static/img/catalogue/b640.jpg",
      "/static/img/catalogue/bg4524.jpg",
      "/static/img/catalogue/bg4526.jpg",
      "/static/img/catalogue/bg4525.jpg"
    ],
    "price": "7467 грн",
    "specs": [
      "висота, мм: 920",
      "ширина, мм: 1050",
      "глибина, мм: 2130",
      "матеріал: дерев'яний масив",
      "вид деревини: сосна",
      "основа під матрац: гнуті ортопедичні ламелі",
      "матеріал покриття: фарба, лак"
    ]
  },
  {
    "name": "Ліжко Монако 140 + вклад",
    "desc": "",
    "images": [
      "/static/img/catalogue/b641.jpg",
      "/static/img/catalogue/bg4527.jpg"
    ],
    "price": "8217 грн",
    "specs": [
      "висота, мм: 840",
      "ширина, мм: 1550",
      "глибина, мм: 2140",
      "матеріал: дерев'яний масив",
      "вид деревини: сосна",
      "основа під матрац: гнуті ортопедичні ламелі",
      "матеріал покриття: фарба, лак"
    ]
  },
  {
    "name": "Ліжко Монако 160 + вклад",
    "desc": "",
    "images": [
      "/static/img/catalogue/b642.jpg",
      "/static/img/catalogue/bg4528.jpg"
    ],
    "price": "8472 грн",
    "specs": [
      "висота, мм: 840",
      "ширина, мм: 1750",
      "глибина, мм: 2140",
      "матеріал: дерев'яний масив",
      "вид деревини: сосна",
      "основа під матрац: гнуті ортопедичні ламелі",
      "матеріал покриття: фарба, лак"
    ]
  },
  {
    "name": "Ліжко Монако 180 + вклад",
    "desc": "",
    "images": [
      "/static/img/catalogue/b643.jpg",
      "/static/img/catalogue/bg4529.jpg"
    ],
    "price": "8725 грн",
    "specs": [
      "висота, мм: 840",
      "ширина, мм: 1950",
      "глибина, мм: 2140",
      "матеріал: дерев'яний масив",
      "вид деревини: сосна",
      "основа під матрац: гнуті ортопедичні ламелі",
      "матеріал покриття: фарба, лак"
    ]
  },
  {
    "name": "Ліжко Монако 90 + вклад",
    "desc": "",
    "images": [
      "/static/img/catalogue/b644.jpg",
      "/static/img/catalogue/bg4530.jpg"
    ],
    "price": "7420 грн",
    "specs": [
      "висота, мм: 840",
      "ширина, мм: 1050",
      "глибина, мм: 2140",
      "матеріал: дерев'яний масив",
      "вид деревини: сосна",
      "основа під матрац: гнуті ортопедичні ламелі",
      "матеріал покриття: фарба, лак"
    ]
  },
  {
    "name": "Ліжко Верона 140 + вклад",
    "desc": "",
    "images": [
      "/static/img/catalogue/b645.jpg",
      "/static/img/catalogue/bg4531.jpg"
    ],
    "price": "7898 грн",
    "specs": [
      "висота, мм: 790",
      "ширина, мм: 1470",
      "глибина, мм: 2270",
      "матеріал: дерев'яний масив",
      "вид деревини: сосна",
      "основа під матрац: гнуті ортопедичні ламелі",
      "матеріал покриття: фарба, лак"
    ]
  },
  {
    "name": "Ліжко Верона 160 + вклад",
    "desc": "",
    "images": [
      "/static/img/catalogue/b646.jpg",
      "/static/img/catalogue/bg4532.jpg"
    ],
    "price": "8142 грн",
    "specs": [
      "висота, мм: 790",
      "ширина, мм: 1670",
      "глибина, мм: 2270",
      "матеріал: дерев'яний масив",
      "вид деревини: сосна",
      "основа під матрац: гнуті ортопедичні ламелі",
      "матеріал покриття: фарба, лак"
    ]
  },
  {
    "name": "Ліжко Верона 180 + вклад",
    "desc": "",
    "images": [
      "/static/img/catalogue/b647.jpg",
      "/static/img/catalogue/bg4533.jpg"
    ],
    "price": "8386 грн",
    "specs": [
      "висота, мм: 790",
      "ширина, мм: 1870",
      "глибина, мм: 2270",
      "матеріал: дерев'яний масив",
      "вид деревини: сосна",
      "основа під матрац: гнуті ортопедичні ламелі",
      "матеріал покриття: фарба, лак"
    ]
  },
  {
    "name": "Ліжко Верона 90 + вклад",
    "desc": "",
    "images": [
      "/static/img/catalogue/b648.jpg",
      "/static/img/catalogue/bg4534.jpg"
    ],
    "price": "7128 грн",
    "specs": [
      "висота, мм: 790",
      "ширина, мм: 970",
      "глибина, мм: 2270",
      "матеріал: дерев'яний масив",
      "вид деревини: сосна",
      "основа під матрац: гнуті ортопедичні ламелі",
      "матеріал покриття: фарба, лак"
    ]
  },
  {
    "name": "Ліжко Мілан 140 + вклад",
    "desc": "",
    "images": [
      "/static/img/catalogue/b649.jpg",
      "/static/img/catalogue/bg4535.jpg"
    ],
    "price": "8058 грн",
    "specs": [
      "висота, мм: 800",
      "ширина, мм: 1550",
      "глибина, мм: 2090",
      "матеріал: дерев'яний масив",
      "вид деревини: сосна",
      "основа під матрац: гнуті ортопедичні ламелі",
      "матеріал покриття: фарба, лак"
    ]
  },
  {
    "name": "Ліжко Мілан 160 + вклад",
    "desc": "",
    "images": [
      "/static/img/catalogue/b650.jpg",
      "/static/img/catalogue/bg4536.jpg"
    ],
    "price": "8307 грн",
    "specs": [
      "висота, мм: 800",
      "ширина, мм: 1750",
      "глибина, мм: 2090",
      "матеріал: дерев'яний масив",
      "вид деревини: сосна",
      "основа під матрац: гнуті ортопедичні ламелі",
      "матеріал покриття: фарба, лак"
    ]
  },
  {
    "name": "Ліжко Мілан 180 + вклад",
    "desc": "",
    "images": [
      "/static/img/catalogue/b651.jpg",
      "/static/img/catalogue/bg4537.jpg"
    ],
    "price": "8556 грн",
    "specs": [
      "висота, мм: 800",
      "ширина, мм: 1950",
      "глибина, мм: 2090",
      "матеріал: дерев'яний масив",
      "вид деревини: сосна",
      "основа під матрац: гнуті ортопедичні ламелі",
      "матеріал покриття: фарба, лак"
    ]
  },
  {
    "name": "Ліжко Мілан 90 + вклад",
    "desc": "",
    "images": [
      "/static/img/catalogue/b652.jpg",
      "/static/img/catalogue/bg4538.jpg"
    ],
    "price": "7272 грн",
    "specs": [
      "висота, мм: 800",
      "ширина, мм: 1050",
      "глибина, мм: 2090",
      "матеріал: дерев'яний масив",
      "вид деревини: сосна",
      "основа під матрац: гнуті ортопедичні ламелі",
      "матеріал покриття: фарба, лак"
    ]
  },
  {
    "name": "Ліжко Прем'єра 140 + вклад",
    "desc": "",
    "images": [
      "/static/img/catalogue/b653.jpg",
      "/static/img/catalogue/bg4540.jpg",
      "/static/img/catalogue/bg4539.jpg"
    ],
    "price": "7273 грн",
    "specs": [
      "висота, мм: 800",
      "ширина, мм: 1520",
      "глибина, мм: 2090",
      "матеріал: дерев'яний масив",
      "вид деревини: сосна",
      "основа під матрац: гнуті ортопедичні ламелі",
      "матеріал покриття: фарба, лак"
    ]
  },
  {
    "name": "Ліжко Прем'єра 160 + вклад",
    "desc": "",
    "images": [
      "/static/img/catalogue/b654.jpg",
      "/static/img/catalogue/bg4542.jpg",
      "/static/img/catalogue/bg4541.jpg"
    ],
    "price": "7498 грн",
    "specs": [
      "висота, мм: 800",
      "ширина, мм: 1720",
      "глибина, мм: 2090",
      "матеріал: дерев'яний масив",
      "вид деревини: сосна",
      "основа під матрац: гнуті ортопедичні ламелі",
      "матеріал покриття: фарба, лак"
    ]
  },
  {
    "name": "Ліжко Прем'єра 180 + вклад",
    "desc": "",
    "images": [
      "/static/img/catalogue/b655.jpg",
      "/static/img/catalogue/bg4544.jpg",
      "/static/img/catalogue/bg4543.jpg"
    ],
    "price": "7722 грн",
    "specs": [
      "висота, мм: 800",
      "ширина, мм: 1920",
      "глибина, мм: 2090",
      "матеріал: дерев'яний масив",
      "вид деревини: сосна",
      "основа під матрац: гнуті ортопедичні ламелі",
      "матеріал покриття: фарба, лак"
    ]
  },
  {
    "name": "Ліжко Прем'єра 90 + вклад",
    "desc": "",
    "images": [
      "/static/img/catalogue/b656.jpg",
      "/static/img/catalogue/bg4546.jpg",
      "/static/img/catalogue/bg4545.jpg"
    ],
    "price": "6565 грн",
    "specs": [
      "висота, мм: 800",
      "ширина, мм: 1020",
      "глибина, мм: 2090",
      "матеріал: дерев'яний масив",
      "вид деревини: сосна",
      "основа під матрац: гнуті ортопедичні ламелі",
      "матеріал покриття: фарба, лак"
    ]
  },
  {
    "name": "Ліжко Новара 140 + вклад",
    "desc": "",
    "images": [
      "/static/img/catalogue/b657.jpg",
      "/static/img/catalogue/bg4547.jpg"
    ],
    "price": "6750 грн",
    "specs": [
      "висота, мм: 695(300)",
      "ширина, мм: 1450",
      "глибина, мм: 2110",
      "матеріал: дерев'яний масив",
      "вид деревини: сосна",
      "основа під матрац: гнуті ортопедичні ламелі",
      "матеріал покриття: фарба, лак"
    ]
  },
  {
    "name": "Ліжко Новара 160 + вклад",
    "desc": "",
    "images": [
      "/static/img/catalogue/b658.jpg",
      "/static/img/catalogue/bg4548.jpg"
    ],
    "price": "6958 грн",
    "specs": [
      "висота, мм: 695(300)",
      "ширина, мм: 1650",
      "глибина, мм: 2110",
      "матеріал: дерев'яний масив",
      "вид деревини: сосна",
      "основа під матрац: гнуті ортопедичні ламелі",
      "матеріал покриття: фарба, лак"
    ]
  },
  {
    "name": "Ліжко Новара 180 + вклад",
    "desc": "",
    "images": [
      "/static/img/catalogue/b659.jpg",
      "/static/img/catalogue/bg4549.jpg"
    ],
    "price": "7168 грн",
    "specs": [
      "висота, мм: 695(300)",
      "ширина, мм: 1850",
      "глибина, мм: 2110",
      "матеріал: дерев'яний масив",
      "вид деревини: сосна",
      "основа під матрац: гнуті ортопедичні ламелі",
      "матеріал покриття: фарба, лак"
    ]
  },
  {
    "name": "Ліжко Новара 90 + вклад",
    "desc": "",
    "images": [
      "/static/img/catalogue/b660.jpg",
      "/static/img/catalogue/bg4550.jpg"
    ],
    "price": "6092 грн",
    "specs": [
      "висота, мм: 695(300)",
      "ширина, мм: 950",
      "глибина, мм: 2110",
      "матеріал: дерев'яний масив",
      "вид деревини: сосна",
      "основа під матрац: гнуті ортопедичні ламелі",
      "матеріал покриття: фарба, лак"
    ]
  },
  {
    "name": "Ліжко Челсі 140 + вклад",
    "desc": "",
    "images": [
      "/static/img/catalogue/b661.jpg",
      "/static/img/catalogue/bg4551.jpg"
    ],
    "price": "7425 грн",
    "specs": [
      "висота, мм: 950",
      "ширина, мм: 1480",
      "глибина, мм: 2190",
      "матеріал: дерев'яний масив",
      "вид деревини: сосна",
      "основа під матрац: гнуті ортопедичні ламелі",
      "матеріал покриття: фарба, лак"
    ]
  },
  {
    "name": "Ліжко Челсі 160 + вклад",
    "desc": "",
    "images": [
      "/static/img/catalogue/b662.jpg",
      "/static/img/catalogue/bg4552.jpg"
    ],
    "price": "7655 грн",
    "specs": [
      "висота, мм: 950",
      "ширина, мм: 1680",
      "глибина, мм: 2190",
      "матеріал: дерев'яний масив",
      "вид деревини: сосна",
      "основа під матрац: гнуті ортопедичні ламелі",
      "матеріал покриття: фарба, лак"
    ]
  },
  {
    "name": "Ліжко Челсі 180 + вклад",
    "desc": "",
    "images": [
      "/static/img/catalogue/b663.jpg",
      "/static/img/catalogue/bg4553.jpg"
    ],
    "price": "7885 грн",
    "specs": [
      "висота, мм: 950",
      "ширина, мм: 1880",
      "глибина, мм: 2190",
      "матеріал: дерев'яний масив",
      "вид деревини: сосна",
      "основа під матрац: гнуті ортопедичні ламелі",
      "матеріал покриття: фарба, лак"
    ]
  },
  {
    "name": "Ліжко Челсі 90 + вклад",
    "desc": "",
    "images": [
      "/static/img/catalogue/b664.jpg",
      "/static/img/catalogue/bg4554.jpg"
    ],
    "price": "6700 грн",
    "specs": [
      "висота, мм: 950",
      "ширина, мм: 980",
      "глибина, мм: 2190",
      "матеріал: дерев'яний масив",
      "вид деревини: сосна",
      "основа під матрац: гнуті ортопедичні ламелі",
      "матеріал покриття: фарба, лак"
    ]
  },
  {
    "name": "Двох'ярусне сімейне ліжко Скандинавія 120/80/200",
    "desc": "",
    "images": [
      "/static/img/catalogue/b665.jpg",
      "/static/img/catalogue/bg4555.jpg",
      "/static/img/catalogue/bg4556.jpg"
    ],
    "price": "15004 грн",
    "specs": [
      "висота, мм: 1700",
      "ширина, мм: 1280",
      "глибина, мм: 2120",
      "матеріал: дерев'яний масив",
      "вид деревини: сосна",
      "основа під матрац: гнуті ортопедичні ламелі",
      "матеріал покриття: фарба, лак"
    ]
  },
  {
    "name": "Двох'ярусне сімейне ліжко Скандинавія 140/90/200",
    "desc": "",
    "images": [
      "/static/img/catalogue/b666.jpg",
      "/static/img/catalogue/bg4557.jpg",
      "/static/img/catalogue/bg4558.jpg"
    ],
    "price": "15455 грн",
    "specs": [
      "висота, мм: 1700",
      "ширина, мм: 1480",
      "глибина, мм: 2120",
      "матеріал: дерев'яний масив",
      "вид деревини: сосна",
      "основа під матрац: гнуті ортопедичні ламелі",
      "матеріал покриття: фарба, лак"
    ]
  },
  {
    "name": "Двох'ярусне  ліжко Скандінавія міні",
    "desc": "",
    "images": [
      "/static/img/catalogue/b667.jpg",
      "/static/img/catalogue/bg4560.jpg",
      "/static/img/catalogue/bg4559.jpg"
    ],
    "price": "12074 грн",
    "specs": [
      "висота, мм: 1740",
      "ширина, мм: 960",
      "глибина, мм: 2120",
      "матеріал: дерев'яний масив",
      "вид деревини: сосна",
      "основа під матрац: гнуті ортопедичні ламелі",
      "матеріал покриття: фарба, лак"
    ]
  },
  {
    "name": "Двох'ярусне сімейне ліжко Аляска 120/80/200",
    "desc": "",
    "images": [
      "/static/img/catalogue/b668.jpg",
      "/static/img/catalogue/bg4561.jpg"
    ],
    "price": "15265 грн",
    "specs": [
      "висота, мм: 1750",
      "ширина, мм: 1360",
      "глибина, мм: 2140",
      "матеріал: дерев'яний масив",
      "вид деревини: сосна",
      "основа під матрац: гнуті ортопедичні ламелі",
      "матеріал покриття: фарба, лак"
    ]
  },
  {
    "name": "Двох'ярусне сімейне ліжко Аляска 140/90/200",
    "desc": "",
    "images": [
      "/static/img/catalogue/b669.jpg",
      "/static/img/catalogue/bg4562.jpg"
    ],
    "price": "15722 грн",
    "specs": [
      "висота, мм: 1750",
      "ширина, мм: 1560",
      "глибина, мм: 2140",
      "матеріал: дерев'яний масив",
      "вид деревини: сосна",
      "основа під матрац: гнуті ортопедичні ламелі",
      "матеріал покриття: фарба, лак"
    ]
  },
  {
    "name": "Двох'ярусне  ліжко Мальта",
    "desc": "",
    "images": [
      "/static/img/catalogue/b670.jpg",
      "/static/img/catalogue/bg4563.jpg",
      "/static/img/catalogue/bg4564.jpg"
    ],
    "price": "14732 грн",
    "specs": [
      "висота, мм: 1740",
      "ширина, мм: 1000",
      "глибина, мм: 2140",
      "матеріал: дерев'яний масив",
      "вид деревини: сосна",
      "основа під матрац: гнуті ортопедичні ламелі",
      "матеріал покриття: фарба, лак"
    ]
  },
  {
    "name": "Двох'ярусне  ліжко Бай-бай",
    "desc": "",
    "images": [
      "/static/img/catalogue/b671.jpg",
      "/static/img/catalogue/bg4565.jpg",
      "/static/img/catalogue/bg4566.jpg"
    ],
    "price": "12012 грн",
    "specs": [
      "висота, мм: 1700",
      "ширина, мм: 1060",
      "глибина, мм: 2120",
      "матеріал: дерев'яний масив",
      "вид деревини: сосна",
      "основа під матрац: гнуті ортопедичні ламелі",
      "матеріал покриття: фарба, лак"
    ]
  },
  {
    "name": "Двох'ярусне  ліжко Жасмін(200х90)",
    "desc": "",
    "images": [
      "/static/img/catalogue/b672.jpg",
      "/static/img/catalogue/bg4568.jpg",
      "/static/img/catalogue/bg4567.jpg"
    ],
    "price": "12370 грн",
    "specs": [
      "висота, мм: 1780",
      "ширина, мм: 970",
      "глибина, мм: 2080",
      "матеріал: дерев'яний масив",
      "вид деревини: сосна",
      "основа під матрац: гнуті ортопедичні ламелі",
      "матеріал покриття: фарба, лак"
    ]
  },
  {
    "name": "Ліжко двоспальне 1.6 Алекса Індастріал / Німфеа Альба",
    "desc": "",
    "images": [
      "/static/img/catalogue/lizhko-2-sp-spalnya-aleksa-svit-mebliv-700x700.jpeg",
      "/static/img/catalogue/lizhko-spalnya-aleksa-svit-mebliv-3-700x700.png",
      "/static/img/catalogue/karkas-lizhko-2sp-svit-mebliv-2-700x700.jpg",
      "/static/img/catalogue/tumba-aleksa-svit-mebliv-1-700x700.jpeg",
      "/static/img/catalogue/spalnya-aleksa-svit-mebliv-700x700.jpeg",
      "/static/img/catalogue/spalnya-aleksa-svit-mebliv-700x700.png"
    ],
    "price": "4926 грн",
    "specs": [
      "Корпус: ДСП",
      "Фасад: ДСП",
      "Товщина ДСП: 1,6 см",
      "Довжина: 206,2 см",
      "Ширина: 164,4 см",
      "Висота: 110 см",
      "Ширина спального місця: 160 см",
      "Довжина спального місця: 200 см",
      "Корпус: Індастріал",
      "Фасад: Німфеа Альба",
      "Комплектація: Можлива комплектація ліжка каркасом СМ",
      "Гарантія: 18 місяців",
      "Країна виробник: Україна"
    ]
  },
  {
    "name": "Ліжко двоспальне 1.6 Амелія Білий / Білий глянець",
    "desc": "",
    "images": [
      "/static/img/catalogue/lizhko-ameliya-svit-mebliv-700x700.jpeg",
      "/static/img/catalogue/spalnya-ameliya-svit-mebliv-700x700.jpeg",
      "/static/img/catalogue/spalnya-amelia-svit-mebliv-2-700x700.png"
    ],
    "price": "4932 грн",
    "specs": [
      "Корпус: ДСП",
      "Фасад: ДСП",
      "Товщина ДСП: 1,6 см",
      "Довжина: 206,5 см",
      "Ширина: 165 см",
      "Висота: 98 см",
      "Ширина спального місця: 160 см",
      "Довжина спального місця: 200 см",
      "Корпус: Білий",
      "Фасад: Білий глянець",
      "Комплектація: Можлива комплектація ліжка каркасом СМ",
      "Гарантія: 18 місяців",
      "Країна виробник: Україна"
    ]
  },
  {
    "name": "Ліжко двоспальне 1.6 Каміла Графіт / Дуб Артизан",
    "desc": "",
    "images": [
      "/static/img/catalogue/lizhko-2sp-16-kamila-hrafit-dub-artizan-700x700.png",
      "/static/img/catalogue/lizhko-kamila-hrafit-dub-artizan-skhema-700x700.jpg",
      "/static/img/catalogue/spalnya-kamila-hrafit-dub-artizan-700x700.jpeg"
    ],
    "price": "5057 грн",
    "specs": [
      "Корпус: ДСП",
      "Фасад: ДСП",
      "Ізголів'я: Тканина",
      "Товщина ДСП: 1,6 см",
      "Довжина: 206 см",
      "Ширина: 169 см",
      "Висота: 100 см",
      "Ширина спального місця: 160 см",
      "Довжина спального місця: 200 см",
      "Корпус: Графіт",
      "Фасад: Дуб артизан / Графіт",
      "Ізголів'я: Багіра 34",
      "Комплектація: Можлива комплектація ліжка каркасом СМ",
      "Гарантія: 18 місяців",
      "Країна виробник: Україна"
    ]
  },
  {
    "name": "Ліжко двоспальне 1.6 Кармен Нова Горіх  / Піно горіх, лак, художній друк",
    "desc": "",
    "images": [
      "/static/img/catalogue/lizhko-karmen-nova-horikh-svit-mebliv-1-700x700.jpeg",
      "/static/img/catalogue/krovat-karmen-novaya-orekh-mir-mebeli-1-700x700.png",
      "/static/img/catalogue/krovat-karmen-novaya-orekh-mir-mebeli-2-700x700.jpeg",
      "/static/img/catalogue/lizhko-karmen-nova-horikh-svit-mebliv-700x700.jpeg",
      "/static/img/catalogue/lizhko-karmen-nova-horikh-svit-mebliv-2-700x700.jpeg",
      "/static/img/catalogue/karkas-lizhko-2sp-svit-mebliv-2-700x700.jpg",
      "/static/img/catalogue/spalnya-karmen-nova-horikh-svit-mebliv-1-700x700.jpeg",
      "/static/img/catalogue/krovat-karmen-novaya-orekh-mir-mebeli-1-700x700.jpeg"
    ],
    "price": "12139 грн",
    "specs": [
      "Корпус: ДСП",
      "Фасад: ДСП",
      "Товщина ДСП: 1,6 см",
      "Довжина: 212 см",
      "Ширина: 181 см",
      "Висота: 125 см",
      "Ширина спального місця: 160 см",
      "Довжина спального місця: 200 см",
      "Корпус: Піно горіх",
      "Фасад: Піно горіх, лак, художній друк",
      "Комплектація: Можлива комплектація ліжка каркасом СМ",
      "Гарантія: 18 місяців",
      "Країна виробник: Україна"
    ]
  },
  {
    "name": "Ліжко двоспальне 1.6 Кармен Нова Піно / Піно лак, художній друк",
    "desc": "",
    "images": [
      "/static/img/catalogue/lizhko-karmen-nova-pyno-svyt-meblyv-700x700.jpeg",
      "/static/img/catalogue/lizhko-karmen-nova-pino-svit-mebliv-3-700x700.jpeg",
      "/static/img/catalogue/shafa-karmen-pino-700x700.jpeg",
      "/static/img/catalogue/krovat-dvuspalnaya-karmen-pino-700x700.jpeg",
      "/static/img/catalogue/spalnya-karmen-nova-pyno-svyt-meblyv-700x700.jpeg",
      "/static/img/catalogue/spalnya_karmen-svit-mebliv-700x700.png",
      "/static/img/catalogue/karkas-lizhko-2sp-svit-mebliv-2-700x700.jpg"
    ],
    "price": "12139 грн",
    "specs": [
      "Корпус: ДСП",
      "Фасад: ДСП",
      "Товщина ДСП: 1,6 см",
      "Довжина: 212 см",
      "Ширина: 181 см",
      "Висота: 125 см",
      "Ширина спального місця: 160 см",
      "Довжина спального місця: 200 см",
      "Корпус: Піно",
      "Фасад: Піно лак, художній друк",
      "Комплектація: Можлива комплектація ліжка каркасом СМ",
      "Гарантія: 18 місяців",
      "Країна виробник: Україна"
    ]
  },
  {
    "name": "Ліжко двоспальне 1.6 Кім Дуб артизан / Білий",
    "desc": "",
    "images": [
      "/static/img/catalogue/lizhko-2-sp-1.6-spalnya-kim-dub-sonoma-bilyy-svit-mebliv-700x700.jpeg",
      "/static/img/catalogue/lizhko-2-sp-spalnya-kim-dub-sonoma-bilyy-700x700.jpg",
      "/static/img/catalogue/spalnya-kim-dub-sonoma-bilyy-svit-mebliv-700x700.jpeg",
      "/static/img/catalogue/spalnya-kim-svit-mebliv-prais-700x700.png"
    ],
    "price": "2381 грн",
    "specs": [
      "Корпус: ДСП",
      "Фасад: ДСП",
      "Товщина ДСП: 1,6 см",
      "Довжина: 2060 см",
      "Ширина: 170 см",
      "Висота: 670 см",
      "Ширина спального місця: 160 см",
      "Довжина спального місця: 200 см",
      "Корпус: Дуб артизан",
      "Фасад: Дуб артизан / Білий",
      "Комплектація: Можлива комплектація ліжка каркасом СМ",
      "Гарантія: 18 місяців",
      "Країна виробник: Україна"
    ]
  },
  {
    "name": "Ліжко двоспальне 1.6 Кім Венге магія / Дуб молочний",
    "desc": "",
    "images": [
      "/static/img/catalogue/lizhko-kim-dub-sonoma-700x700.jpg",
      "/static/img/catalogue/spalnya-kim-dub-molochnyy-venhe-mahiya-svit-mebliv-2-700x700.jpg",
      "/static/img/catalogue/spalnya-kim-svit-mebliv-prais-700x700.png",
      "/static/img/catalogue/karkas-lizhko-2sp-svit-mebliv-2-700x700.jpg"
    ],
    "price": "2844 грн",
    "specs": [
      "Корпус: ДСП",
      "Фасад: ДСП",
      "Товщина ДСП: 1,6 см",
      "Довжина: 2060 см",
      "Ширина: 170 см",
      "Висота: 670 см",
      "Ширина спального місця: 160 см",
      "Довжина спального місця: 200 см",
      "Корпус: Венге магія",
      "Фасад: Венге магія / Дуб молочний",
      "Комплектація: Можлива комплектація ліжка каркасом СМ",
      "Гарантія: 18 місяців",
      "Країна виробник: Україна"
    ]
  },
  {
    "name": "Ліжко двоспальне 1.4 Круїз Білий/Дакар",
    "desc": "",
    "images": [
      "/static/img/catalogue/lizhko-2-sp-1.6-kruyiz-svit-meblivjpg-700x700.jpg",
      "/static/img/catalogue/lizhko-1.4-kruyiz-bilyy-dakar-700x700.jpeg",
      "/static/img/catalogue/lizhko-1.4-kruyiz-bilyy-dakar-2-700x700.jpeg",
      "/static/img/catalogue/spalnya-kruyiz-svit-mebliv-700x700.jpg",
      "/static/img/catalogue/kruyiz-bilyy-dakar-700x700.jpeg",
      "/static/img/catalogue/kruyiz-bilyy-dakar-2-700x700.png"
    ],
    "price": "3391 грн",
    "specs": [
      "Корпус: ДСП",
      "Фасад: ДСП",
      "Товщина ДСП: 1,6 см",
      "Довжина: 204,5 см",
      "Ширина: 144,2 см",
      "Висота: 87,5 см",
      "Ширина спального місця: 140 см",
      "Довжина спального місця: 200 см",
      "Корпус: Білий",
      "Фасад: Білий, Дакар",
      "Комплектація: Можлива комплектація ліжка каркасом СМ",
      "Гарантія: 18 місяців",
      "Країна виробник: Україна"
    ]
  },
  {
    "name": "Ліжко двоспальне 1.6 Круїз Білий/Дакар",
    "desc": "",
    "images": [
      "/static/img/catalogue/lizhko-2-sp-1.6-kruyiz-svit-meblivjpg-700x700.jpg",
      "/static/img/catalogue/lizhko-1.6-kruyiz-bilyy-dakar-4-700x700.png",
      "/static/img/catalogue/lizhko-1.6-kruyiz-bilyy-dakar-2-700x700.jpeg",
      "/static/img/catalogue/spalnya-kruyiz-svit-mebliv-700x700.jpg",
      "/static/img/catalogue/kruyiz-bilyy-dakar-700x700.jpeg",
      "/static/img/catalogue/kruyiz-bilyy-dakar-2-700x700.png"
    ],
    "price": "3710 грн",
    "specs": [
      "Корпус: ДСП",
      "Фасад: ДСП",
      "Товщина ДСП: 1,6 см",
      "Довжина: 206,2 см",
      "Ширина: 164,2 см",
      "Висота: 87,5 см",
      "Ширина спального місця: 160 см",
      "Довжина спального місця: 200 см",
      "Корпус: Білий",
      "Фасад: Білий, Дакар",
      "Комплектація: Можлива комплектація ліжка каркасом СМ",
      "Гарантія: 18 місяців",
      "Країна виробник: Україна"
    ]
  },
  {
    "name": "Ліжко двоярусне Саванна Дуб крафт сірий/Льон",
    "desc": "",
    "images": [
      "/static/img/catalogue/2-sp-savanna-main-700x700.jpg",
      "/static/img/catalogue/2-sp-savanna-3-700x700.jpg",
      "/static/img/catalogue/2sp-savanna-linen-2-700x700.jpg",
      "/static/img/catalogue/2-sp-savanna-4-700x700.jpg",
      "/static/img/catalogue/2-sp-savanna-5-700x700.jpg",
      "/static/img/catalogue/2-sp-savanna-6-700x700.jpg"
    ],
    "price": "12108 грн",
    "specs": [
      "Корпус: ДСП",
      "Фасад: МДФ",
      "Товщина ДСП: 1,6 см",
      "Довжина: 194,5 см",
      "Висота: 114 см",
      "Глибина: 86 см",
      "Ширина спального місця: 190 см",
      "Довжина спального місця: 80 см",
      "Корпус: Дуб крафт сірий",
      "Фасад: Льон",
      "Комплектація: Ліжко комплектується підкладом та не потребує каркасу",
      "Гарантія: 18 місяців",
      "Країна виробник: Україна"
    ]
  },
  {
    "name": "Ліжко двоспальне 1.2 Круїз Білий/Дакар",
    "desc": "",
    "images": [
      "/static/img/catalogue/lizhko-2-sp-1.6-kruyiz-svit-meblivjpg-700x700.jpg",
      "/static/img/catalogue/lizhko-1.6-kruyiz-bilyy-dakar-4-700x700.png",
      "/static/img/catalogue/lizhko-1.6-kruyiz-bilyy-dakar-2-700x700.jpeg",
      "/static/img/catalogue/spalnya-kruyiz-svit-mebliv-700x700.jpg",
      "/static/img/catalogue/kruyiz-bilyy-dakar-700x700.jpeg"
    ],
    "price": "3052 грн",
    "specs": [
      "Корпус: ДСП",
      "Фасад: ДСП",
      "Товщина ДСП: 1,6 см",
      "Довжина: 206,2 см",
      "Ширина: 124,2 см",
      "Висота: 87,5 см",
      "Ширина спального місця: 120 см",
      "Довжина спального місця: 200 см",
      "Корпус: Білий",
      "Фасад: Білий, Дакар",
      "Комплектація: Без матрасу та каркасу",
      "Гарантія: 18 місяців",
      "Країна виробник: Україна"
    ]
  },
  {
    "name": "Ліжко односпальне Твіст 1",
    "desc": "",
    "images": [
      "/static/img/catalogue/dytyacha-twist-blue-12-700x700.jpg",
      "/static/img/catalogue/lizko-svit-mebliv-tvist-90h200-sm-234215-product_slider-700x700.jpg"
    ],
    "price": "2666 грн",
    "specs": [
      "Корпус: ДСП",
      "Фасад: ДСП",
      "Матеріал м'якої частини: Тканина",
      "Товщина ДСП: 1,6 см",
      "Довжина: 206,2 см",
      "Ширина: 95,6 см",
      "Висота: 90 см",
      "Ширина спального місця: 90 см",
      "Довжина спального місця: 200 см",
      "Корпус: Білий",
      "Гарантія: 18 місяців",
      "Країна виробник: Україна"
    ]
  },
  {
    "name": "Ліжко односпальне 2Ш Твіст 1",
    "desc": "",
    "images": [
      "/static/img/catalogue/dytyacha-twist-blue-11-700x700.jpg",
      "/static/img/catalogue/ligko-2sh-twist-1-2-700x700.jpg",
      "/static/img/catalogue/ligko-2sh-twist-1-3-700x700.jpg"
    ],
    "price": "6082 грн",
    "specs": [
      "Корпус: ДСП",
      "Фасад: ДСП",
      "Матеріал м'якої частини: Тканина",
      "Товщина ДСП: 1,6 см",
      "Довжина: 205 см",
      "Ширина: 94,5 см",
      "Висота: 90 см",
      "Ширина спального місця: 90 см",
      "Довжина спального місця: 200 см",
      "Корпус: Білий",
      "Фасад: Білий/Глиняний сірий/Холодний блакитний",
      "Комплектація: Ліжко комплектується ексклюзивним каркасом «СМ»",
      "Гарантія: 18 місяців",
      "Країна виробник: Україна"
    ]
  },
  {
    "name": "Ліжко двоярусне Саванна Дуб крафт сірий/Блакитна лагуна",
    "desc": "",
    "images": [
      "/static/img/catalogue/ligko-dvojarusne-savanna-blue-lagoon-700x700.jpg",
      "/static/img/catalogue/2-sp-savanna-6-700x700.jpg",
      "/static/img/catalogue/ligko-dvojarusne-savanna-blue-lagoon-2-700x700.jpg",
      "/static/img/catalogue/2-sp-savanna-4-700x700.jpg",
      "/static/img/catalogue/2-sp-savanna-5-700x700.jpg"
    ],
    "price": "12108 грн",
    "specs": [
      "Корпус: ДСП",
      "Фасад: МДФ",
      "Товщина ДСП: 1,6 см",
      "Довжина: 194,5 см",
      "Висота: 114 см",
      "Глибина: 86 см",
      "Ширина спального місця: 190 см",
      "Довжина спального місця: 80 см",
      "Корпус: Дуб крафт сірий",
      "Фасад: Блакитна лагуна",
      "Комплектація: Ліжко комплектується підкладом та не потребує каркасу",
      "Гарантія: 18 місяців",
      "Країна виробник: Україна"
    ]
  },
  {
    "name": "Ліжко-гірка Саванна Дуб крафт сірий/Блакитна лагуна",
    "desc": "",
    "images": [
      "/static/img/catalogue/ligko-girka-savanna-blue-lagoon-700x700.jpg"
    ],
    "price": "11790 грн",
    "specs": [
      "Корпус: ДСП",
      "Фасад: МДФ",
      "Товщина ДСП: 1,6 см",
      "Довжина: 195 см",
      "Висота: 180,5 см",
      "Глибина: 86 см",
      "Ширина спального місця: 190 см",
      "Довжина спального місця: 80 см",
      "Корпус: Дуб крафт сірий",
      "Фасад: Блакитна лагуна",
      "Комплектація: Ліжко комплектується підкладом та не потребує каркасу",
      "Гарантія: 18 місяців",
      "Країна виробник: Україна"
    ]
  },
  {
    "name": "Ліжко-гірка Саванна Дуб крафт сірий/Льон",
    "desc": "",
    "images": ["/static/img/catalogue/ligko-girka-savanna-linen-700x700.jpg"],
    "price": "11790 грн",
    "specs": [
      "Корпус: ДСП",
      "Фасад: МДФ",
      "Товщина ДСП: 1,6 см",
      "Довжина: 195 см",
      "Висота: 180,5 см",
      "Глибина: 86 см",
      "Ширина спального місця: 190 см",
      "Довжина спального місця: 80 см",
      "Корпус: Дуб крафт сірий",
      "Фасад: Льон",
      "Комплектація: Ліжко комплектується підкладом та не потребує каркасу",
      "Гарантія: 18 місяців",
      "Країна виробник: Україна"
    ]
  },
  {
    "name": "Ліжко двоспальне 1.2 Лілея нова Артвуд світлий / Антрацит",
    "desc": "",
    "images": [
      "/static/img/catalogue/lizhko-lileya-nova-artvud-antratsyt-700x700.png",
      "/static/img/catalogue/lizhko-lileya-nova-artvud-antratsyt-700x700.jpeg",
      "/static/img/catalogue/spalnya-artvud-antratsyt-svit-mebliv-700x700.jpeg"
    ],
    "price": "3017 грн",
    "specs": [
      "Корпус: ДСП",
      "Фасад: ДСП",
      "Товщина ДСП: 1,6 см",
      "Довжина: 206,2 см",
      "Ширина: 124,2 см",
      "Висота: 87,5 см",
      "Ширина спального місця: 120 см",
      "Довжина спального місця: 200 см",
      "Корпус: Артвуд світлий",
      "Фасад: Артвуд світлий / Антрацит",
      "Комплектація: Без матраца та каркаса",
      "Гарантія: 18 місяців",
      "Країна виробник: Україна"
    ]
  },
  {
    "name": "Ліжко двоспальне 1.2 Лілея нова Дуб гранж колоніальний/ Антрацит",
    "desc": "",
    "images": [
      "/static/img/catalogue/lizhko-lileya-nova-dub-hranzh-kolonialnyy-700x700.jpeg",
      "/static/img/catalogue/spalnya-lileya-nova-dub-hranzh-kolonialnyy-svit-mebliv-700x700.jpeg",
      "/static/img/catalogue/karkas-lizhko-2sp-svit-mebliv-2-700x700.jpg"
    ],
    "price": "3017 грн",
    "specs": [
      "Корпус: ДСП",
      "Фасад: ДСП",
      "Товщина ДСП: 1,6 см",
      "Довжина: 206,2 см",
      "Ширина: 124,2 см",
      "Висота: 87,5 см",
      "Ширина спального місця: 120 см",
      "Довжина спального місця: 200 см",
      "Корпус: Дуб гранж колоніальний",
      "Фасад: Дуб гранж колоніальний / Антрацит",
      "Комплектація: Без матраца та каркаса",
      "Гарантія: 18 місяців",
      "Країна виробник: Україна"
    ]
  },
  {
    "name": "Ліжко двоспальне 1.4 Лілея нова Артвуд світлий / Антрацит",
    "desc": "",
    "images": [
      "/static/img/catalogue/lizhko-lileya-nova-artvud-antratsyt-700x700.png",
      "/static/img/catalogue/lizhko-lileya-nova-artvud-antratsyt-700x700.jpeg",
      "/static/img/catalogue/spalnya-artvud-antratsyt-svit-mebliv-700x700.jpeg"
    ],
    "price": "3286 грн",
    "specs": [
      "Корпус: ДСП",
      "Фасад: ДСП",
      "Товщина ДСП: 1,6 см",
      "Довжина: 206,2 см",
      "Ширина: 144,2 см",
      "Висота: 87,5 см",
      "Ширина спального місця: 140 см",
      "Довжина спального місця: 200 см",
      "Корпус: Артвуд світлий",
      "Фасад: Артвуд світлий / Антрацит",
      "Комплектація: Без матраца та каркаса",
      "Гарантія: 18 місяців",
      "Країна виробник: Україна"
    ]
  },
  {
    "name": "Ліжко двоспальне 1.4 Лілея нова Дуб гранж колоніальний/ Антрацит",
    "desc": "",
    "images": [
      "/static/img/catalogue/lizhko-lileya-nova-dub-hranzh-kolonialnyy-700x700.jpeg",
      "/static/img/catalogue/spalnya-lileya-nova-dub-hranzh-kolonialnyy-svit-mebliv-700x700.jpeg",
      "/static/img/catalogue/karkas-lizhko-2sp-svit-mebliv-2-700x700.jpg"
    ],
    "price": "3286 грн",
    "specs": [
      "Корпус: ДСП",
      "Фасад: ДСП",
      "Товщина ДСП: 1,6 см",
      "Довжина: 206,2 см",
      "Ширина: 144,2 см",
      "Висота: 87,5 см",
      "Ширина спального місця: 140 см",
      "Довжина спального місця: 200 см",
      "Корпус: Дуб гранж колоніальний",
      "Фасад: Дуб гранж колоніальний / Антрацит",
      "Комплектація: Без матраца та каркаса",
      "Гарантія: 18 місяців",
      "Країна виробник: Україна"
    ]
  },
  {
    "name": "Ліжко односпальне Саванна Дуб крафт сірий",
    "desc": "",
    "images": ["/static/img/catalogue/ligko-odnospalne-savanna-700x700.jpg"],
    "price": "2813 грн",
    "specs": [
      "Корпус: ДСП",
      "Фасад: ДСП",
      "Товщина ДСП: 1,6 см",
      "Довжина: 85 см",
      "Висота: 48 см",
      "Глибина: 195 см",
      "Ширина спального місця: 80 см",
      "Довжина спального місця: 190 см",
      "Корпус: Дуб крафт сірий",
      "Фасад: Дуб крафт сірий",
      "Комплектація: Ліжко комплектується підкладом та не потребує каркасу",
      "Гарантія: 18 місяців",
      "Країна виробник: Україна"
    ]
  },
  {
    "name": "Ліжко двоспальне 1.6 Лілея нова Дуб гранж колоніальний/ Антрацит",
    "desc": "",
    "images": [
      "/static/img/catalogue/lizhko-lileya-nova-dub-hranzh-kolonialnyy-700x700.jpeg",
      "/static/img/catalogue/spalnya-lileya-nova-dub-hranzh-kolonialnyy-svit-mebliv-700x700.jpeg",
      "/static/img/catalogue/spalnya-lileya-nova-dub-hranzh-kolonialnyy-700x700.png",
      "/static/img/catalogue/karkas-lizhko-2sp-svit-mebliv-2-700x700.jpg"
    ],
    "price": "3568 грн",
    "specs": [
      "Корпус: ДСП",
      "Фасад: ДСП",
      "Товщина ДСП: 1,6 см",
      "Довжина: 206,2 см",
      "Ширина: 164,2 см",
      "Висота: 87,5 см",
      "Ширина спального місця: 160 см",
      "Довжина спального місця: 200 см",
      "Корпус: Дуб гранж колоніальний",
      "Фасад: Дуб гранж колоніальний / Антрацит",
      "Комплектація: Ліжко комплектується ексклюзивним каркасом СМ",
      "Гарантія: 18 місяців",
      "Країна виробник: Україна"
    ]
  },
  {
    "name": "Ліжко двоспальне 1.6 Лілея нова Артвуд світлий / Антрацит",
    "desc": "",
    "images": [
      "/static/img/catalogue/lizhko-lileya-nova-artvud-antratsyt-700x700.png",
      "/static/img/catalogue/lizhko-lileya-nova-artvud-antratsyt-700x700.jpeg",
      "/static/img/catalogue/spalnya-artvud-antratsyt-svit-mebliv-700x700.jpeg",
      "/static/img/catalogue/spalnya-lileya-nova-artvud-antratsyt-svit-mebliv-1-700x700.png"
    ],
    "price": "3568 грн",
    "specs": [
      "Корпус: ДСП",
      "Фасад: ДСП",
      "Товщина ДСП: 1,6 см",
      "Довжина: 206,2 см",
      "Ширина: 164,2 см",
      "Висота: 87,5 см",
      "Ширина спального місця: 160 см",
      "Довжина спального місця: 200 см",
      "Корпус: Артвуд світлий",
      "Фасад: Артвуд світлий / Антрацит",
      "Комплектація: Ліжко комплектується ексклюзивним каркасом СМ",
      "Гарантія: 18 місяців",
      "Країна виробник: Україна"
    ]
  },
  {
    "name": "Ліжко двоспальне 1.4 Б'янко Білий / Чорний/ Дуб Аппалачі",
    "desc": "",
    "images": [
      "/static/img/catalogue/ligko-1.4-700x700.jpg",
      "/static/img/catalogue/byanko-pidlitkova-chorna-vstavka-scaled-1-700x700.jpg",
      "/static/img/catalogue/byanko-pidlitkova-vstavka-dub-appalachi-scaled-1-700x700.jpg",
      "/static/img/catalogue/karkas-dvosp-pid-ligko-700x700.jpg"
    ],
    "price": "5743 грн",
    "specs": [
      "Корпус: ДСП",
      "Вставки: ДСП",
      "Ізголів'я: МДФ",
      "Довжина: 206,2 см",
      "Ширина: 145 см",
      "Висота: 98 см",
      "Спальне місце: 140х200см",
      "Ширина спального місця: 140 см",
      "Довжина спального місця: 200 см",
      "Корпус: Білий",
      "Вставки: Чорний / Дуб Аппалачі",
      "Ізголів'я: Білий, глянець",
      "Ортопедичний каркас: За додаткову плату",
      "Підйомний механізм: Немає",
      "Гарантія: 18 місяців",
      "Країна виробник: Україна"
    ]
  },
  {
    "name": "Ліжко двоспальне 1.6 Б'янко Білий / Чорний / Дуб Аппалачі",
    "desc": "",
    "images": [
      "/static/img/catalogue/ligko-1.6-700x700.jpg",
      "/static/img/catalogue/byanko-spalnya-vstavka-appalachi-scaled-2-700x700.jpg",
      "/static/img/catalogue/byanko-spalnya-01-scaled-700x700.jpg",
      "/static/img/catalogue/karkas-dvosp-pid-ligko-700x700.jpg"
    ],
    "price": "6184 грн",
    "specs": [
      "Корпус: ДСП",
      "Вставки: ДСП",
      "Ізголів'я: МДФ",
      "Довжина: 206,2 см",
      "Ширина: 165 см",
      "Висота: 98 см",
      "Спальне місце: 160х200 см",
      "Ширина спального місця: 160 см",
      "Довжина спального місця: 200 см",
      "Корпус: Білий",
      "Вставки: Чорний / Дуб Аппалачі",
      "Ізголів'я: Білий, глянець",
      "Ортопедичний каркас: За додаткову плату",
      "Підйомний механізм: Немає",
      "Гарантія: 18 місяців",
      "Країна виробник: Україна"
    ]
  },
  {
    "name": "Ліжко двоспальне 1.2 Б'янко Білий / Чорний/ Дуб Аппалачі",
    "desc": "",
    "images": [
      "/static/img/catalogue/ligko-1.2-700x700.jpg",
      "/static/img/catalogue/byanko-pidlitkova-vstavka-dub-appalachi-scaled-1-700x700.jpg",
      "/static/img/catalogue/byanko-pidlitkova-chorna-vstavka-scaled-1-700x700.jpg",
      "/static/img/catalogue/karkas-pid-ligko-700x700.jpg"
    ],
    "price": "4824 грн",
    "specs": [
      "Корпус: ДСП",
      "Вставки: ДСП",
      "Ізголів'я: МДФ",
      "Довжина: 206,2 см",
      "Ширина: 125 см",
      "Висота: 98 см",
      "Спальне місце: 120х200см",
      "Ширина спального місця: 120 см",
      "Довжина спального місця: 200 см",
      "Корпус: Білий",
      "Вставки: Чорний / Дуб Аппалачі",
      "Ізголів'я: Білий, глянець",
      "Ортопедичний каркас: За додаткову плату",
      "Підйомний механізм: Немає",
      "Гарантія: 18 місяців",
      "Країна виробник: Україна"
    ]
  },
  {
    "name": "Ліжко односпальне Б'янко Білий / Чорний / Дуб Аппалачі",
    "desc": "",
    "images": [
      "/static/img/catalogue/ligko-1sp-700x700.jpg",
      "/static/img/catalogue/byanko-pidlitkova-vstavka-dub-appalachi-scaled-2-700x700.jpg",
      "/static/img/catalogue/karkas-pid-ligko-700x700.jpg"
    ],
    "price": "3659 грн",
    "specs": [
      "Корпус: ДСП",
      "Вставки: ДСП",
      "Ізголів'я: МДФ",
      "Довжина: 206,2 см",
      "Ширина: 95 см",
      "Висота: 98 см",
      "Спальне місце: 90х200 см",
      "Ширина спального місця: 90 см",
      "Довжина спального місця: 200 см",
      "Корпус: Білий",
      "Вставки: Чорний / Дуб Аппалачі",
      "Ізголів'я: Білий",
      "Ортопедичний каркас: За додаткову плату",
      "Підйомний механізм: Немає",
      "Гарантія: 18 місяців",
      "Країна виробник: Україна"
    ]
  },
  {
    "name": "Ліжко двоспальне 1.6 Лотос Дуб гранж колоніальний / Антрацит",
    "desc": "",
    "images": [
      "/static/img/catalogue/lizhko-2sp-1.6-lotos-svit-mebliv-700x700.jpg",
      "/static/img/catalogue/spalnya-lotos-dsp-dub-hranzh-antratsyt-700x700.jpeg",
      "/static/img/catalogue/spalnya-lotos-svit-mebliv-700x700.jpeg",
      "/static/img/catalogue/spalnya-lotos-dsp-dub-hranzh-antratsyt-700x700.png"
    ],
    "price": "2522 грн",
    "specs": [
      "Корпус: ДСП",
      "Фасад: ДСП",
      "Товщина ДСП: 1,6 см",
      "Довжина: 206 см",
      "Ширина: 170 см",
      "Висота: 67 см",
      "Ширина спального місця: 160 см",
      "Довжина спального місця: 200 см",
      "Корпус: Дуб гранж колоніальний",
      "Фасад: Дуб гранж колоніальний / Антрацит",
      "Комплектація: Можлива комплектація ліжка каркасом СМ",
      "Гарантія: 18 місяців",
      "Країна виробник: Україна"
    ]
  },
  {
    "name": "Ліжко двоспальне 1.6 Марія Дуб борас / Біле золото",
    "desc": "",
    "images": [
      "/static/img/catalogue/lizhko-mariya-bile-zoloto-dub-boras-700x700.jpeg",
      "/static/img/catalogue/spalnya-katrin-horikh-patina-700x700.jpeg",
      "/static/img/catalogue/maryia-orekh-patina-shkaf-700x700.png",
      "/static/img/catalogue/spalnya-maria-dub-boros-bile-zoloto-700x700.png"
    ],
    "price": "5077 грн",
    "specs": [
      "Корпус: ДСП",
      "Фасад: ДСП",
      "Товщина ДСП: 1,6 см",
      "Довжина: 206,2 см",
      "Ширина: 164, 2 см",
      "Висота: 97,5 см",
      "Ширина спального місця: 160 см",
      "Довжина спального місця: 200 см",
      "Корпус: Дуб борас",
      "Фасад: Біле золото",
      "Комплектація: Можлива комплектація ліжка каркасом СМ",
      "Гарантія: 18 місяців",
      "Країна виробник: Україна"
    ]
  },
  {
    "name": "Ліжко двоспальне 1.6 з м'яким бильцем Ніколь Білий / Біле дерево, патина",
    "desc": "",
    "images": [
      "/static/img/catalogue/lishko-2-sp-nikol-bilyy-bile-derevo-patyna-700x700.jpeg",
      "/static/img/catalogue/lizhko-z-myakym-byltsem-nikol-bile-derevo-1-700x700.jpeg",
      "/static/img/catalogue/lizhko-z-myakym-byltsem-nikol-bile-derevo-2-700x700.jpeg",
      "/static/img/catalogue/spalnya-nikol-bile-derevo-1-700x700.jpeg",
      "/static/img/catalogue/lizhko-nikol-bile-derevo-2-700x700.jpeg",
      "/static/img/catalogue/spalnya-nikol-bilyy-bile-derevo-patyna-700x700.jpeg",
      "/static/img/catalogue/spalnya-nikol-bile-derevo-2-700x700.png",
      "/static/img/catalogue/karkas-lizhko-2sp-svit-mebliv-2-700x700.jpg"
    ],
    "price": "9603 грн",
    "specs": [
      "Корпус: ДСП",
      "Фасад: МДФ",
      "Товщина ДСП: 1,6 см",
      "Довжина: 211,5 см",
      "Ширина: 183,5 см",
      "Висота: 114,5 см",
      "Ширина спального місця: 160 см",
      "Довжина спального місця: 200 см",
      "Корпус: Білий",
      "Фасад: Біле дерево, патина",
      "Комплектація: Можлива комплектація ліжка каркасом СМ",
      "Гарантія: 18 місяців",
      "Країна виробник: Україна"
    ]
  },
  {
    "name": "Ліжко двоспальне 1.6 Ніколь Білий / Біле дерево, патина",
    "desc": "",
    "images": [
      "/static/img/catalogue/lizhko-2-sp-1.8-nikol-bilyy-bile-derevo-patyna-700x700.jpeg",
      "/static/img/catalogue/spalnya-nikol-bile-derevo-700x700.png",
      "/static/img/catalogue/lizko-nikol-bile-derevo-1-700x700.jpeg",
      "/static/img/catalogue/lizhko-nikol-bile-derevo-2-700x700.jpeg",
      "/static/img/catalogue/spalnya-nikol-bilyy-bile-derevo-patyna-700x700.jpeg",
      "/static/img/catalogue/spalnya-nikol-bile-derevo-2-700x700.png",
      "/static/img/catalogue/karkas-lizhko-2sp-svit-mebliv-2-700x700.jpg"
    ],
    "price": "8365 грн",
    "specs": [
      "Корпус: ДСП",
      "Фасад: МДФ",
      "Товщина ДСП: 1,6 см",
      "Довжина: 211,5 см",
      "Ширина: 183,5 см",
      "Висота: 114,5 см",
      "Ширина спального місця: 160 см",
      "Довжина спального місця: 200 см",
      "Корпус: Білий",
      "Фасад: Біле дерево, патина",
      "Комплектація: Можлива комплектація ліжка каркасом СМ",
      "Гарантія: 18 місяців",
      "Країна виробник: Україна"
    ]
  },
  {
    "name": "Ліжко двоспальне 1.6 Ромбо Артвуд світлий / Білий",
    "desc": "",
    "images": [
      "/static/img/catalogue/lizhko-2-sp-1.6-spalnya-rombo-svit-mebliv-700x700.jpeg",
      "/static/img/catalogue/lizhko-2-sp-1.6-spalnya-rombo-svit-mebliv-1-700x700.jpeg",
      "/static/img/catalogue/lizhko-2-sp-1.6-spalnya-rombo-svit-mebliv-1-700x700.png",
      "/static/img/catalogue/karkas-lizhko-2sp-svit-mebliv-2-700x700.jpg",
      "/static/img/catalogue/-spalnya-rombo-svit-mebliv-700x700.jpeg",
      "/static/img/catalogue/spalnya-rombo-svit-mebliv-1-700x700.png"
    ],
    "price": "4698 грн",
    "specs": [
      "Корпус: ДСП",
      "Фасад: ДСП",
      "Ізголів'я: Тканина",
      "Товщина ДСП: 1,6 см",
      "Довжина: 206,2 см",
      "Ширина: 165 см",
      "Висота: 110 см",
      "Ширина спального місця: 160 см",
      "Довжина спального місця: 200 см",
      "Корпус: Артвуд світлий",
      "Фасад: Артвуд світлий / Білий",
      "Комплектація: Можлива комплектація ліжка каркасом СМ",
      "Гарантія: 18 місяців",
      "Країна виробник: Україна"
    ]
  },
  {
    "name": "Ліжко Саманта 1 без підйомного механізму",
    "desc": "",
    "images": [
      "/static/img/catalogue/samanta-1-main-700x700.jpg",
      "/static/img/catalogue/samanta-1-2-700x700.jpg"
    ],
    "price": "13414 грн",
    "specs": [
      "Корпус: ДСП",
      "Довжина: 218 см",
      "Ширина: 132 см, 152 см, 172 см, 192 см, 212 см",
      "Висота: 112 см",
      "Ширина спального місця: 120 см, 140 см, 160 см, 180 см, 200 см",
      "Довжина спального місця: 200 см",
      "Комплектація: Металевий каркас",
      "Підйомний механізм: Ні",
      "Гарантія: 18 місяців",
      "Країна виробник: Україна"
    ]
  },
  {
    "name": "Ліжко Саманта 1 з підйомним механізмом",
    "desc": "",
    "images": [
      "/static/img/catalogue/samanta-1-main-700x700.jpg",
      "/static/img/catalogue/samanta-1-2-700x700.jpg",
      "/static/img/catalogue/samanta-1-3-700x700.jpg",
      "/static/img/catalogue/samanta-3-6-700x700.jpg",
      "/static/img/catalogue/samanta-pidjomniy-mechanism-2-700x700.jpg",
      "/static/img/catalogue/samanta-pidjomniy-mechanism-700x700.jpg",
      "/static/img/catalogue/samanta-1-4-700x700.jpg"
    ],
    "price": "15651 грн",
    "specs": [
      "Корпус: ДСП",
      "Довжина: 218 см",
      "Ширина: 132 см, 152 см, 172 см, 192 см, 212 см",
      "Висота: 112 см",
      "Ширина спального місця: 120 см, 140 см, 160 см, 180 см, 200 см",
      "Довжина спального місця: 200 см",
      "Комплектація: Металевий каркас",
      "Підйомний механізм: Так",
      "Ніша для речей: Так",
      "Гарантія: 18 місяців",
      "Країна виробник: Україна"
    ]
  },
  {
    "name": "Ліжко Саманта 2 без підйомного механізму",
    "desc": "",
    "images": [
      "/static/img/catalogue/samanta-2-main-700x700.jpg",
      "/static/img/catalogue/samanta-2-2-700x700.jpg"
    ],
    "price": "13414 грн",
    "specs": [
      "Корпус: ДСП",
      "Довжина: 218 см",
      "Ширина: 132 см, 152 см, 172 см, 192 см, 212 см",
      "Висота: 112 см",
      "Ширина спального місця: 120 см, 140 см, 160 см, 180 см, 200 см",
      "Довжина спального місця: 200 см",
      "Комплектація: Металевий каркас",
      "Підйомний механізм: Ні",
      "Гарантія: 18 місяців",
      "Країна виробник: Україна"
    ]
  },
  {
    "name": "Ліжко Саманта 2 з підйомним механізмом",
    "desc": "",
    "images": [
      "/static/img/catalogue/samanta-2-main-700x700.jpg",
      "/static/img/catalogue/samanta-2-2-700x700.jpg",
      "/static/img/catalogue/samanta-3-6-700x700.jpg",
      "/static/img/catalogue/samanta-pidjomniy-mechanism-2-700x700.jpg",
      "/static/img/catalogue/samanta-pidjomniy-mechanism-700x700.jpg",
      "/static/img/catalogue/samanta-1-4-700x700.jpg"
    ],
    "price": "15651 грн",
    "specs": [
      "Корпус: ДСП",
      "Довжина: 218 см",
      "Ширина: 132 см, 152 см, 172 см, 192 см, 212 см",
      "Висота: 112 см",
      "Ширина спального місця: 120 см, 140 см, 160 см, 180 см, 200 см",
      "Довжина спального місця: 200 см",
      "Комплектація: Металевий каркас",
      "Підйомний механізм: Так",
      "Ніша для речей: Так",
      "Гарантія: 18 місяців",
      "Країна виробник: Україна"
    ]
  },
  {
    "name": "Ліжко Саманта 3 без підйомного механізму",
    "desc": "",
    "images": [
      "/static/img/catalogue/samanta-3-main-700x700.jpg",
      "/static/img/catalogue/samanta-3-2-700x700.jpg",
      "/static/img/catalogue/samanta-3-3-700x700.jpg",
      "/static/img/catalogue/samanta-3-4-700x700.jpg",
      "/static/img/catalogue/samanta-3-5-700x700.jpg"
    ],
    "price": "13414 грн",
    "specs": [
      "Корпус: ДСП",
      "Довжина: 218 см",
      "Ширина: 132 см, 152 см, 172 см, 192 см, 212 см",
      "Висота: 112 см",
      "Ширина спального місця: 120 см, 140 см, 160 см, 180 см, 200 см",
      "Довжина спального місця: 200 см",
      "Комплектація: Металевий каркас",
      "Підйомний механізм: Ні",
      "Гарантія: 18 місяців",
      "Країна виробник: Україна"
    ]
  },
  {
    "name": "Ліжко Саманта 3 з підйомним механізмом",
    "desc": "",
    "images": [
      "/static/img/catalogue/samanta-3-main-700x700.jpg",
      "/static/img/catalogue/samanta-3-2-700x700.jpg",
      "/static/img/catalogue/samanta-3-4-700x700.jpg",
      "/static/img/catalogue/samanta-3-5-700x700.jpg",
      "/static/img/catalogue/samanta-3-3-700x700.jpg",
      "/static/img/catalogue/samanta-3-6-700x700.jpg",
      "/static/img/catalogue/samanta-3-7-700x700.jpg",
      "/static/img/catalogue/samanta-pidjomniy-mechanism-2-700x700.jpg",
      "/static/img/catalogue/samanta-pidjomniy-mechanism-700x700.jpg",
      "/static/img/catalogue/samanta-1-4-700x700.jpg"
    ],
    "price": "15651 грн",
    "specs": [
      "Корпус: ДСП",
      "Довжина: 218 см",
      "Ширина: 132 см, 152 см, 172 см, 192 см, 212 см",
      "Висота: 112 см",
      "Ширина спального місця: 120 см, 140 см, 160 см, 180 см, 200 см",
      "Довжина спального місця: 200 см",
      "Комплектація: Металевий каркас",
      "Підйомний механізм: Так",
      "Ніша для речей: Так",
      "Гарантія: 18 місяців",
      "Країна виробник: Україна"
    ]
  },
  {
    "name": "Ліжко Саманта 4",
    "desc": "",
    "images": [
      "/static/img/catalogue/samanta-4-2-700x700.jpg",
      "/static/img/catalogue/samanta-4-1-700x700.jpg"
    ],
    "price": "12540 грн",
    "specs": [
      "Корпус: ДСП",
      "Довжина: 211 см",
      "Ширина: 102 см",
      "Висота: 108 см",
      "Ширина спального місця: 200 см",
      "Довжина спального місця: 90 см",
      "Комплектація: Металевий каркас",
      "Підйомний механізм: Ні",
      "Ніша для речей: Немає",
      "Гарантія: 18 місяців",
      "Країна виробник: Україна"
    ]
  },
  {
    "name": "Ліжко двоспальне 1.6 Соня Венге магія / Дуб молочний",
    "desc": "",
    "images": [
      "/static/img/catalogue/lizhko-sonya-wenge-magic-milk-oak-700x700.jpeg",
      "/static/img/catalogue/lizhko-sonya-venhe-mahiya-dub-molochnyy-4-700x700.jpeg",
      "/static/img/catalogue/karkas-lizhko-2sp-svit-mebliv-2-700x700.jpg",
      "/static/img/catalogue/spalnya-sonya-venhe-mahiya-dub-molochnyy-svit-mebliv-700x700.jpeg",
      "/static/img/catalogue/spalnya-sonya-venhe-mahiya-dub-molochnyy-700x700.jpeg",
      "/static/img/catalogue/spalnya-sonya-venhe-mahiya-dub-molochnyy-700x700.png"
    ],
    "price": "3125 грн",
    "specs": [
      "Корпус: ДСП",
      "Фасад: ДСП",
      "Товщина ДСП: 1,6 см",
      "Довжина: 206 см",
      "Ширина: 170 см",
      "Висота: 67 см",
      "Ширина спального місця: 160 см",
      "Довжина спального місця: 200 см",
      "Корпус: Венге магія",
      "Фасад: Венге магія / Дуб молочний",
      "Комплектація: Можлива комплектація ексклюзивним каркасом СМ за додаткову плату",
      "Гарантія: 18 місяців",
      "Країна виробник: Україна"
    ]
  },
  {
    "name": "Ліжко двоспальне 1.6 Соня Артвуд світлий / Антрацит",
    "desc": "",
    "images": [
      "/static/img/catalogue/lizhko-sonya-antratsyt-artvud-svitlyy-700x700.jpeg",
      "/static/img/catalogue/karkas-lizhko-2sp-svit-mebliv-2-700x700.jpg",
      "/static/img/catalogue/spalnya-sonya-artvud-svitlyy-antratsyt-svit-mebliv-700x700.jpeg",
      "/static/img/catalogue/spalnya-sona-artwood-antracit-svit-mebliv-700x700.jpg"
    ],
    "price": "2584 грн",
    "specs": [
      "Корпус: ДСП",
      "Фасад: ДСП",
      "Товщина ДСП: 1,6 см",
      "Довжина: 206 см",
      "Ширина: 170 см",
      "Висота: 67 см",
      "Ширина спального місця: 160 см",
      "Довжина спального місця: 200 см",
      "Корпус: Артвуд світлий",
      "Фасад: Артвуд світлий / Антрацит",
      "Комплектація: Можлива комплектація ексклюзивним каркасом СМ за додаткову плату",
      "Гарантія: 18 місяців",
      "Країна виробник: Україна"
    ]
  },
  {
    "name": "Ліжко двоспальне 1.6 Вівіан Артвуд світлий / Індастріал",
    "desc": "",
    "images": [
      "/static/img/catalogue/lizhko-2-sp-1.6-spalnya-vivian-svit-mebliv-700x700.jpeg",
      "/static/img/catalogue/-spalnya-vivian-svit-mebliv-3-700x700.png",
      "/static/img/catalogue/lizhko-svit-mebli-vivian-3-700x700.png",
      "/static/img/catalogue/spalnya-vivian-svit-mebliv-2-700x700.png",
      "/static/img/catalogue/spalnya-vivian-svit-mebliv-700x700.jpeg",
      "/static/img/catalogue/spalnya-vivian-svit-mebliv-4-700x700.png"
    ],
    "price": "4624 грн",
    "specs": [
      "Корпус: ДСП",
      "Фасад: ДСП",
      "Ізголів'я: Тканина",
      "Товщина ДСП: 1,6 см",
      "Довжина: 206,2 см",
      "Ширина: 164,2 см",
      "Висота: 110 см",
      "Ширина спального місця: 160 см",
      "Довжина спального місця: 200 см",
      "Корпус: Артвуд світлий",
      "Фасад: Артвуд світлий / Індастріал",
      "Комплектація: Ліжко комплектується ексклюзивним каркасом СМ",
      "Гарантія: 18 місяців",
      "Країна виробник: Україна"
    ]
  },
  {
    "name": "Ліжко двоспальне 1.6 Жасмін Білий / Білий, лак, художній друк",
    "desc": "",
    "images": [
      "/static/img/catalogue/lizhko-zhasmin-bilyy-lak-svit-mebliv-700x700.jpeg",
      "/static/img/catalogue/lishko-zhasmin-venetsiya-nova-pino-bezh-700x700.jpg",
      "/static/img/catalogue/lizhko-shema-zhasmin-venetsiya-nova-pino-bezh-1-700x700.jpeg",
      "/static/img/catalogue/spalnya-zhasmin-bilyy-lak-svit-mebliv-700x700.jpeg",
      "/static/img/catalogue/jasmin-svit-mebliv-2-700x700.png"
    ],
    "price": "10656 грн",
    "specs": [
      "Корпус: ДСП",
      "Фасад: ДСП",
      "Довжина: 215 см",
      "Ширина: 179 см",
      "Висота: 123 см",
      "Ширина спального місця: 160 см",
      "Довжина спального місця: 200 см",
      "Корпус: Білий",
      "Фасад: Білий, лак, художній друк",
      "Комплектація: Можлива комплектація ліжка каркасом СМ",
      "Гарантія: 18 місяців",
      "Країна виробник: Україна"
    ]
  },
  {
    "name": "Ліжко Б'янка ВудЛайн",
    "desc": "Бюджетна модель. Це проста та надійна конструкція без зайвих елементів.\nОсновні параметри:\n• Каркас: міцний дерев'яний брус та ЛДСП.\n• Наповнення: поєднання повсті, пінополіуретану та синтепону.\n• Оббивка: доступний широкий вибір тканин різних цінових категорій.\n• Механізм: газліфт.\n• Наповнення спальної частини на вибір: матрац або рама з ламелями.\nЗа доплату можливо, вартість уточнюйте:\n• Корпус ламінований\n• Збільшення спального місця та розміру\nЦіна вказана в початковій категорії тканини Саванна Нова і може не відповідати фотографіям. Щоб детально ознайомитись з асортиментом тканин, відвідайте наш магазин або підберіть тканину на сайті виробника тканини.",
    "images": [
      "/static/img/catalogue/byanka-1000x668.jpg",
      "/static/img/catalogue/byanka2-1000x668.jpg",
      "/static/img/catalogue/byanka1-1000x668.jpg",
      "/static/img/catalogue/byanka-krovat1-1000x668.jpg",
      "/static/img/catalogue/byanka-krovat-1000x668.jpg"
    ],
    "price": "9210 грн",
    "specs": [
      "Ширина : 800-1600 мм",
      "Глибина : 2070 мм",
      "Висота : 1100 мм",
      "Виробник : ВудЛайн",
      "Наповнення спального місця : з матрацом",
      "Матеріал : фанера, ЛДСП",
      "Ширина: 800-1600 мм",
      "Глибина: 2070 мм",
      "Висота: 1100 мм",
      "Спальне місце: 800-1600х2000",
      "Виробник: ВудЛайн",
      "Наповнення спального місця: з матрацом",
      "Матеріал: фанера, ЛДСП",
      "Основа: ЛДСП",
      "Механизм: газліфт"
    ]
  },
  {
    "name": "Ліжко Моніка ВудЛайн",
    "desc": "Бюджетна модель. Це проста та надійна конструкція без зайвих елементів.\nОсновні параметри:\n• Каркас: міцний дерев'яний брус та ЛДСП.\n• Наповнення: поєднання повсті, пінополіуретану та синтепону.\n• Оббивка: доступний широкий вибір тканин різних цінових категорій.\n• Механізм: газліфт.\n• Наповнення спальної частини на вибір: матрац або рама з ламелями.\nЗа доплату можливо, вартість уточнюйте:\n• Корпус ламінований\n• Збільшення спального місця та розміру\nЦіна вказана в початковій категорії тканини Саванна Нова і може не відповідати фотографіям. Щоб детально ознайомитись з асортиментом тканин, відвідайте наш магазин або підберіть тканину на сайті виробника тканини.",
    "images": [
      "/static/img/catalogue/monika-1000x668.jpg",
      "/static/img/catalogue/monika2-1000x668.jpg",
      "/static/img/catalogue/monika1-1000x668.jpg"
    ],
    "price": "10570 грн",
    "specs": [
      "Ширина : 800-1600 мм",
      "Глибина : 2070 мм",
      "Висота : 1100 мм",
      "Виробник : ВудЛайн",
      "Наповнення спального місця : з матрацом",
      "Матеріал : фанера, ЛДСП",
      "Ширина: 800-1600 мм",
      "Глибина: 2070 мм",
      "Висота: 1100 мм",
      "Спальне місце: 800-1600х2000",
      "Виробник: ВудЛайн",
      "Наповнення спального місця: з матрацом",
      "Матеріал: фанера, ЛДСП",
      "Основа: ЛДСП",
      "Механизм: газліфт"
    ]
  },
  {
    "name": "Ліжко Сафарі ВудЛайн",
    "desc": "Бюджетна модель. Це проста та надійна конструкція без зайвих елементів.\nОсновні параметри:\n• Каркас: міцний дерев'яний брус та ЛДСП.\n• Наповнення: поєднання повсті, пінополіуретану та синтепону.\n• Оббивка: доступний широкий вибір тканин різних цінових категорій.\n• Механізм: газліфт.\n• Наповнення спальної частини на вибір: матрац або рама з ламелями.\nЗа доплату можливо, вартість уточнюйте:\n• Корпус ламінований\n• Збільшення спального місця та розміру\nЦіна вказана в початковій категорії тканини Саванна Нова і може не відповідати фотографіям. Щоб детально ознайомитись з асортиментом тканин, відвідайте наш магазин або підберіть тканину на сайті виробника тканини.",
    "images": [
      "/static/img/catalogue/safari-1000x668.jpg",
      "/static/img/catalogue/safari2-1000x668.jpg",
      "/static/img/catalogue/safari1-1000x668.jpg"
    ],
    "price": "9500 грн",
    "specs": [
      "Ширина : 800-1600 мм",
      "Глибина : 2070 мм",
      "Висота : 1100 мм",
      "Виробник : ВудЛайн",
      "Наповнення спального місця : з матрацом",
      "Матеріал : фанера, ЛДСП",
      "Ширина: 800-1600 мм",
      "Глибина: 2070 мм",
      "Висота: 1100 мм",
      "Спальне місце: 800-1600х2000",
      "Виробник: ВудЛайн",
      "Наповнення спального місця: з матрацом",
      "Матеріал: фанера, ЛДСП",
      "Основа: ЛДСП",
      "Механизм: газліфт"
    ]
  },
  {
    "name": "Ліжко Мрія ВудЛайн",
    "desc": "Бюджетна модель. Це проста та надійна конструкція без зайвих елементів.\nОсновні параметри:\n• Каркас: міцний дерев'яний брус та ЛДСП.\n• Наповнення: поєднання повсті, пінополіуретану та синтепону.\n• Оббивка: доступний широкий вибір тканин різних цінових категорій.\n• Механізм: газліфт.\n• Наповнення спальної частини на вибір: матрац або рама з ламелями.\nЗа доплату можливо, вартість уточнюйте:\n• Корпус ламінований\n• Збільшення спального місця та розміру\nЦіна вказана в початковій категорії тканини Саванна Нова і може не відповідати фотографіям. Щоб детально ознайомитись з асортиментом тканин, відвідайте наш магазин або підберіть тканину на сайті виробника тканини.",
    "images": [
      "/static/img/catalogue/mriya-1000x668.jpg",
      "/static/img/catalogue/mriya1-1000x668.jpg"
    ],
    "price": "10990 грн",
    "specs": [
      "Ширина : 800-1600 мм",
      "Глибина : 2070 мм",
      "Висота : 1100 мм",
      "Виробник : ВудЛайн",
      "Наповнення спального місця : з матрацом",
      "Матеріал : фанера, ЛДСП",
      "Ширина: 800-1600 мм",
      "Глибина: 2070 мм",
      "Висота: 1100 мм",
      "Спальне місце: 800-1600х2000",
      "Виробник: ВудЛайн",
      "Наповнення спального місця: з матрацом",
      "Матеріал: фанера, ЛДСП",
      "Основа: ЛДСП",
      "Механизм: газліфт"
    ]
  },
  {
    "name": "Ліжко Мілана ВудЛайн",
    "desc": "Бюджетна модель. Це проста та надійна конструкція без зайвих елементів.\nОсновні параметри:\n• Каркас: міцний дерев'яний брус та ЛДСП.\n• Наповнення: поєднання повсті, пінополіуретану та синтепону.\n• Оббивка: доступний широкий вибір тканин різних цінових категорій.\n• Механізм: газліфт.\n• Наповнення спальної частини на вибір: матрац або рама з ламелями.\nЗа доплату можливо, вартість уточнюйте:\n• Корпус ламінований\n• Збільшення спального місця та розміру\nЦіна вказана в початковій категорії тканини Саванна Нова і може не відповідати фотографіям. Щоб детально ознайомитись з асортиментом тканин, відвідайте наш магазин або підберіть тканину на сайті виробника тканини.",
    "images": [
      "/static/img/catalogue/milana-1000x668.jpg",
      "/static/img/catalogue/milana2-1000x668.jpg",
      "/static/img/catalogue/milana1-1000x668.jpg"
    ],
    "price": "10990 грн",
    "specs": [
      "Ширина : 800-1600 мм",
      "Глибина : 2070 мм",
      "Висота : 1100 мм",
      "Виробник : ВудЛайн",
      "Наповнення спального місця : з матрацом",
      "Матеріал : фанера, ЛДСП",
      "Ширина: 800-1600 мм",
      "Глибина: 2070 мм",
      "Висота: 1100 мм",
      "Спальне місце: 800-1600х2000",
      "Виробник: ВудЛайн",
      "Наповнення спального місця: з матрацом",
      "Матеріал: фанера, ЛДСП",
      "Основа: ЛДСП",
      "Механизм: газліфт"
    ]
  },
  {
    "name": "Ліжко Ріо ВудЛайн",
    "desc": "Бюджетна модель. Це проста та надійна конструкція без зайвих елементів.\nОсновні параметри:\n• Каркас: міцний дерев'яний брус та ЛДСП.\n• Наповнення: поєднання повсті, пінополіуретану та синтепону.\n• Оббивка: доступний широкий вибір тканин різних цінових категорій.\n• Механізм: газліфт.\n• Наповнення спальної частини на вибір: матрац або рама з ламелями.\nЗа доплату можливо, вартість уточнюйте:\n• Корпус ламінований\n• Збільшення спального місця та розміру\nЦіна вказана в початковій категорії тканини Саванна Нова і може не відповідати фотографіям. Щоб детально ознайомитись з асортиментом тканин, відвідайте наш магазин або підберіть тканину на сайті виробника тканини.",
    "images": [
      "/static/img/catalogue/rio-1000x668.jpg",
      "/static/img/catalogue/rio1-1000x668.jpg"
    ],
    "price": "10990 грн",
    "specs": [
      "Ширина : 800-1600 мм",
      "Глибина : 2070 мм",
      "Висота : 1100 мм",
      "Виробник : ВудЛайн",
      "Наповнення спального місця : з матрацом",
      "Матеріал : фанера, ЛДСП",
      "Ширина: 800-1600 мм",
      "Глибина: 2070 мм",
      "Висота: 1100 мм",
      "Спальне місце: 800-1600х2000",
      "Виробник: ВудЛайн",
      "Наповнення спального місця: з матрацом",
      "Матеріал: фанера, ЛДСП",
      "Основа: ЛДСП",
      "Механизм: газліфт"
    ]
  },
  {
    "name": "Ліжко Лінет ВудЛайн",
    "desc": "Бюджетна модель. Це проста та надійна конструкція без зайвих елементів.\nОсновні параметри:\n• Каркас: міцний дерев'яний брус та ЛДСП.\n• Наповнення: поєднання повсті, пінополіуретану та синтепону.\n• Оббивка: доступний широкий вибір тканин різних цінових категорій.\n• Механізм: газліфт.\n• Наповнення спальної частини на вибір: матрац або рама з ламелями.\nЗа доплату можливо, вартість уточнюйте:\n• Корпус ламінований\n• Збільшення спального місця та розміру\nЦіна вказана в початковій категорії тканини Саванна Нова і може не відповідати фотографіям. Щоб детально ознайомитись з асортиментом тканин, відвідайте наш магазин або підберіть тканину на сайті виробника тканини.",
    "images": [
      "/static/img/catalogue/linet-1000x668.jpg",
      "/static/img/catalogue/linet2-1000x668.jpg",
      "/static/img/catalogue/linet1-1000x668.jpg"
    ],
    "price": "10990 грн",
    "specs": [
      "Ширина : 800-1600 мм",
      "Глибина : 2070 мм",
      "Висота : 1100 мм",
      "Виробник : ВудЛайн",
      "Наповнення спального місця : з матрацом",
      "Матеріал : фанера, ЛДСП",
      "Ширина: 800-1600 мм",
      "Глибина: 2070 мм",
      "Висота: 1100 мм",
      "Спальне місце: 800-1600х2000",
      "Виробник: ВудЛайн",
      "Наповнення спального місця: з матрацом",
      "Матеріал: фанера, ЛДСП",
      "Основа: ЛДСП",
      "Механизм: газліфт"
    ]
  },
  {
    "name": "Ліжко дитяче Соня (з матрацом) ВудЛайн",
    "desc": "Бюджетна модель. Це проста та надійна конструкція без зайвих елементів.\nОсновні параметри:\n• Каркас: міцний дерев'яний брус та ЛДСП.\n• Наповнення: поєднання повсті, пінополіуретану та синтепону.\n• Оббивка: доступний широкий вибір тканин різних цінових категорій.\n• Механізм: газліфт.\nЗа доплату можливо, вартість уточнюйте:\n• Корпус ламінований\n• Збільшення спального місця та розміру\nЦіна вказана в початковій категорії тканини Саванна Нова і може не відповідати фотографіям. Щоб детально ознайомитись з асортиментом тканин, відвідайте наш магазин або підберіть тканину на сайті виробника тканини.",
    "images": [
      "/static/img/catalogue/sonya-krovat-1000x668.jpg",
      "/static/img/catalogue/sonya-krovat2-1000x668.jpg",
      "/static/img/catalogue/sonya-krovat1-1000x668.jpg"
    ],
    "price": "11520 грн",
    "specs": [
      "Ширина : 2000 мм",
      "Глибина : 900 мм",
      "Висота : 800 мм",
      "Виробник : ВудЛайн",
      "Наповнення спального місця : з матрацом",
      "Матеріал : фанера, ЛДСП",
      "Ширина: 2000 мм",
      "Глибина: 900 мм",
      "Висота: 800 мм",
      "Спальне місце: 800х1900",
      "Виробник: ВудЛайн",
      "Наповнення спального місця: з матрацом",
      "Матеріал: фанера, ЛДСП",
      "Основа: ЛДСП",
      "Механизм: газліфт"
    ]
  },
  {
    "name": "Ліжко дитяче Дрім (з матрацом) ВудЛайн",
    "desc": "Бюджетна модель. Це проста та надійна конструкція без зайвих елементів.\nОсновні параметри:\n• Каркас: міцний дерев'яний брус та ЛДСП.\n• Наповнення: поєднання повсті, пінополіуретану та синтепону.\n• Оббивка: доступний широкий вибір тканин різних цінових категорій.\n• Механізм: газліфт.\nЗа доплату можливо, вартість уточнюйте:\n• Корпус ламінований\n• Збільшення спального місця та розміру\nЦіна вказана в початковій категорії тканини Саванна Нова і може не відповідати фотографіям. Щоб детально ознайомитись з асортиментом тканин, відвідайте наш магазин або підберіть тканину на сайті виробника тканини.",
    "images": ["/static/img/catalogue/drim-krovat-1000x668.jpg"],
    "price": "12210 грн",
    "specs": [
      "Ширина : 2000 мм",
      "Глибина : 900 мм",
      "Висота : 800 мм",
      "Виробник : ВудЛайн",
      "Наповнення спального місця : з матрацом",
      "Матеріал : фанера, ЛДСП",
      "Ширина: 2000 мм",
      "Глибина: 900 мм",
      "Висота: 800 мм",
      "Спальне місце: 800х1900",
      "Виробник: ВудЛайн",
      "Наповнення спального місця: з матрацом",
      "Матеріал: фанера, ЛДСП",
      "Основа: ЛДСП",
      "Механизм: газліфт"
    ]
  },
  {
    "name": "Ліжко дитяче Діана (з матрацом) ВудЛайн",
    "desc": "Бюджетна модель. Це проста та надійна конструкція без зайвих елементів.\nОсновні параметри:\n• Каркас: міцний дерев'яний брус та ЛДСП.\n• Наповнення: поєднання повсті, пінополіуретану та синтепону.\n• Оббивка: доступний широкий вибір тканин різних цінових категорій.\n• Механізм: газліфт.\nЗа доплату можливо, вартість уточнюйте:\n• Корпус ламінований\n• Збільшення спального місця та розміру\nЦіна вказана в початковій категорії тканини Саванна Нова і може не відповідати фотографіям. Щоб детально ознайомитись з асортиментом тканин, відвідайте наш магазин або підберіть тканину на сайті виробника тканини.",
    "images": [
      "/static/img/catalogue/diana-krovat-1000x668.jpg",
      "/static/img/catalogue/diana-krovat3-1000x668.jpg",
      "/static/img/catalogue/diana-krovat2-1000x668.jpg",
      "/static/img/catalogue/diana-krovat1-1000x668.jpg"
    ],
    "price": "12890 грн",
    "specs": [
      "Ширина : 2000 мм",
      "Глибина : 900 мм",
      "Висота : 800 мм",
      "Виробник : ВудЛайн",
      "Наповнення спального місця : з матрацом",
      "Матеріал : фанера, ЛДСП",
      "Ширина: 2000 мм",
      "Глибина: 900 мм",
      "Висота: 800 мм",
      "Спальне місце: 800х1900",
      "Виробник: ВудЛайн",
      "Наповнення спального місця: з матрацом",
      "Матеріал: фанера, ЛДСП",
      "Основа: ЛДСП",
      "Механизм: газліфт"
    ]
  }
]
